{
  "updated": "2026-07-10T08:43:06.014673+00:00",
  "count": 150,
  "items": [
    {
      "title": "Purbaya nilai integritas ASN jadi kunci daya saing RI di pasar global",
      "link": "https://www.antaranews.com/berita/5644099/purbaya-nilai-integritas-asn-jadi-kunci-daya-saing-ri-di-pasar-global",
      "summary": "Menteri Keuangan (Menkeu) Purbaya Yudhi Sadewa menilai integritas aparatur sipil negara (ASN) menjadi salah satu faktor ...",
      "published": "2026-07-10T08:41:46+00:00",
      "source": "Antara News",
      "groups": [
        "Government / Policy"
      ],
      "matched": [
        "menteri"
      ],
      "big": false,
      "id": "53dfe5c60761b189"
    },
    {
      "title": "Polri bekali capaja Akpol pemahaman geopolitik untuk jaga stabilitas",
      "link": "https://www.antaranews.com/berita/5644097/polri-bekali-capaja-akpol-pemahaman-geopolitik-untuk-jaga-stabilitas",
      "summary": "Kepolisian Negara Republik Indonesia membekali 282 calon perwira remaja (capaja) Akademi Kepolisian (Akpol) Angkatan ...",
      "published": "2026-07-10T08:39:17+00:00",
      "source": "Antara News",
      "groups": [
        "Geopolitics"
      ],
      "matched": [
        "geopolitik"
      ],
      "big": false,
      "id": "763627d663283b5a"
    },
    {
      "title": "Di Lombok Barat, Prabowo resmikan serentak lima bendungan di Indonesia",
      "link": "https://www.antaranews.com/berita/5644095/di-lombok-barat-prabowo-resmikan-serentak-lima-bendungan-di-indonesia",
      "summary": "Presiden Prabowo Subianto meresmikan secara serentak lima bendungan di lima daerah Indonesia dalam acara yang ...",
      "published": "2026-07-10T08:37:40+00:00",
      "source": "Antara News",
      "groups": [
        "Government / Policy"
      ],
      "matched": [
        "Prabowo"
      ],
      "big": false,
      "id": "9f4a83c2e4703fd4"
    },
    {
      "title": "KPK dalami jumlah uang yang ingin dikasih Bupati Kuansing untuk Menhut",
      "link": "https://www.antaranews.com/berita/5644084/kpk-dalami-jumlah-uang-yang-ingin-dikasih-bupati-kuansing-untuk-menhut",
      "summary": "Komisi Pemberantasan Korupsi (KPK) menyatakan masih mendalami jumlah uang yang ingin dikasih oleh Bupati Kuantan ...",
      "published": "2026-07-10T08:22:38+00:00",
      "source": "Antara News",
      "groups": [
        "Government / Policy"
      ],
      "matched": [
        "KPK"
      ],
      "big": false,
      "id": "5eb8d46a92a533ac"
    },
    {
      "title": "KPK akui punya kewenangan panggil Menhut usai terima laporan penolakan gratifikasi",
      "link": "https://www.antaranews.com/berita/5644079/kpk-akui-punya-kewenangan-panggil-menhut-usai-terima-laporan-penolakan-gratifikasi",
      "summary": "Komisi Pemberantasan Korupsi (KPK) mengakui mempunyai kewenangan untuk memanggil Raja Juli Antoni seusai menerima ...",
      "published": "2026-07-10T08:21:10+00:00",
      "source": "Antara News",
      "groups": [
        "Government / Policy"
      ],
      "matched": [
        "KPK"
      ],
      "big": false,
      "id": "2fa263f187ecd666"
    },
    {
      "title": "Pemerintah terbitkan Inpres Penyelamatan Gajah Sumatera dan Kalimantan",
      "link": "https://www.antaranews.com/berita/5644075/pemerintah-terbitkan-inpres-penyelamatan-gajah-sumatera-dan-kalimantan",
      "summary": "Menteri Kehutanan (Menhut) Raja Juli Antoni mengumumkan Presiden Prabowo Subianto resmi menerbitkan Instruksi Presiden ...",
      "published": "2026-07-10T08:17:47+00:00",
      "source": "Antara News",
      "groups": [
        "Government / Policy"
      ],
      "matched": [
        "Prabowo",
        "menteri"
      ],
      "big": false,
      "id": "f6f636913112cc42"
    },
    {
      "title": "Menhan pastikan YTP siap untuk menjaga dan bangun wilayah Tuban",
      "link": "https://www.antaranews.com/berita/5644072/menhan-pastikan-ytp-siap-untuk-menjaga-dan-bangun-wilayah-tuban",
      "summary": "Menteri Pertahanan (Menhan) Sjafrie Sjamsoeddin memastikan personel Yonif Teritorial Pembangunan (YTP) dalam keadaan ...",
      "published": "2026-07-10T08:16:07+00:00",
      "source": "Antara News",
      "groups": [
        "Government / Policy"
      ],
      "matched": [
        "menteri"
      ],
      "big": false,
      "id": "77c697618411fe8d"
    },
    {
      "title": "Airlangga sebut program B50 bisa hemat devisa Rp177 triliun",
      "link": "https://www.antaranews.com/berita/5644048/airlangga-sebut-program-b50-bisa-hemat-devisa-rp177-triliun",
      "summary": "Menteri Koordinator Bidang Perekonomian Airlangga Hartarto mengatakan, penerapan program biodiesel B50 dapat menghemat ...",
      "published": "2026-07-10T08:07:12+00:00",
      "source": "Antara News",
      "groups": [
        "Government / Policy"
      ],
      "matched": [
        "menteri"
      ],
      "big": false,
      "id": "f7f13e5ef014889a"
    },
    {
      "title": "Menteri Bahlil: Rachmat Gobel berjasa bina pengusaha muda-dunia usaha",
      "link": "https://www.antaranews.com/berita/5644047/menteri-bahlil-rachmat-gobel-berjasa-bina-pengusaha-muda-dunia-usaha",
      "summary": "Menteri Energi dan Sumber Daya Mineral (ESDM) Bahlil Lahadalia mengenang Anggota DPR RI dan Menteri Perdagangan periode ...",
      "published": "2026-07-10T08:05:59+00:00",
      "source": "Antara News",
      "groups": [
        "Government / Policy"
      ],
      "matched": [
        "DPR",
        "menteri"
      ],
      "big": false,
      "id": "10f9e001256c5bea"
    },
    {
      "title": "DPR minta harmonisasi regulasi daerah diperkuat cegah tumpang tindih",
      "link": "https://www.antaranews.com/berita/5644032/dpr-minta-harmonisasi-regulasi-daerah-diperkuat-cegah-tumpang-tindih",
      "summary": "Anggota Komisi XIII DPR RI Marinus Gea meminta agar harmonisasi regulasi di tingkat daerah diperkuat untuk mencegah ...",
      "published": "2026-07-10T08:03:45+00:00",
      "source": "Antara News",
      "groups": [
        "Government / Policy"
      ],
      "matched": [
        "DPR"
      ],
      "big": false,
      "id": "609e8755f174158d"
    },
    {
      "title": "KPK: Yaqut sudah ditahan kembali pascaoperasi",
      "link": "https://www.antaranews.com/berita/5644029/kpk-yaqut-sudah-ditahan-kembali-pascaoperasi",
      "summary": "Komisi Pemberantasan Korupsi (KPK) mengumumkan tersangka kasus dugaan korupsi kuota haji Yaqut Cholil Qoumas (YCQ) ...",
      "published": "2026-07-10T08:02:04+00:00",
      "source": "Antara News",
      "groups": [
        "Government / Policy"
      ],
      "matched": [
        "KPK"
      ],
      "big": false,
      "id": "2a4599b39987e404"
    },
    {
      "title": "Resmi IPO hari ini, RANS bantah rumor terkait dengan pencucian uang",
      "link": "https://www.antaranews.com/berita/5644017/resmi-ipo-hari-ini-rans-bantah-rumor-terkait-dengan-pencucian-uang",
      "summary": "PT RANS Entertainment Indonesia Tbk (kode saham: RANS) membantah rumor yang beredar di masyarakat bahwa perusahaan ...",
      "published": "2026-07-10T07:57:13+00:00",
      "source": "Antara News",
      "groups": [
        "Global Finance"
      ],
      "matched": [
        "IPO"
      ],
      "big": false,
      "id": "3049ad65a18712fc"
    },
    {
      "title": "ADB pertahankan proyeksi ekonomi Indonesia 5,2 persen pada 2026",
      "link": "https://www.antaranews.com/berita/5644015/adb-pertahankan-proyeksi-ekonomi-indonesia-52-persen-pada-2026",
      "summary": "Asian Development Bank (ADB) mempertahankan proyeksi pertumbuhan ekonomi Indonesia sebesar 5,2 persen pada 2026, ...",
      "published": "2026-07-10T07:54:41+00:00",
      "source": "Antara News",
      "groups": [
        "Global Finance",
        "Macro / Economy"
      ],
      "matched": [
        "ADB",
        "pertumbuhan ekonomi"
      ],
      "big": false,
      "id": "bf313600d5f233ca"
    },
    {
      "title": "KPK sita logam mulia dan miliaran rupiah terkait OTT Bupati Sukoharjo",
      "link": "https://www.antaranews.com/berita/5644009/kpk-sita-logam-mulia-dan-miliaran-rupiah-terkait-ott-bupati-sukoharjo",
      "summary": "Komisi Pemberantasan Korupsi (KPK) menyita barang bukti berupa logam mulia hingga uang berjumlah miliaran rupiah ...",
      "published": "2026-07-10T07:53:52+00:00",
      "source": "Antara News",
      "groups": [
        "Government / Policy",
        "Macro / Economy"
      ],
      "matched": [
        "KPK",
        "OTT",
        "rupiah"
      ],
      "big": true,
      "id": "acdc05ca32531fa4"
    },
    {
      "title": "Pemprov PBD hibahkan anggaran Rp1,9 miliar dukung pembinaan parpol",
      "link": "https://www.antaranews.com/berita/5644005/pemprov-pbd-hibahkan-anggaran-rp19-miliar-dukung-pembinaan-parpol",
      "summary": "Pemerintah Provinsi Papua Barat Daya (PBD) menghibahkan anggaran tahun 2026 senilai Rp1,9 miliar pada 2026 untuk ...",
      "published": "2026-07-10T07:53:49+00:00",
      "source": "Antara News",
      "groups": [
        "Government / Policy"
      ],
      "matched": [
        "anggaran"
      ],
      "big": false,
      "id": "5c0ea32aa962b6df"
    },
    {
      "title": "Perbarui informasi, KPK tangkap 18 orang terkait OTT Bupati Sukoharjo",
      "link": "https://www.antaranews.com/berita/5644001/perbarui-informasi-kpk-tangkap-18-orang-terkait-ott-bupati-sukoharjo",
      "summary": "Komisi Pemberantasan Korupsi (KPK) memperbarui informasi yang telah disampaikan sebelumnya&nbsp;dan menyatakan sempat ...",
      "published": "2026-07-10T07:53:38+00:00",
      "source": "Antara News",
      "groups": [
        "Government / Policy"
      ],
      "matched": [
        "KPK",
        "OTT"
      ],
      "big": false,
      "id": "985bcd8f7204b5a7"
    },
    {
      "title": "KLH lanjutkan proses penyelidikan TPA Jatiwaringin usai pemadaman",
      "link": "https://www.antaranews.com/berita/5643997/klh-lanjutkan-proses-penyelidikan-tpa-jatiwaringin-usai-pemadaman",
      "summary": "Menteri Lingkungan Hidup (LH) Moh. Jumhur Hidayat menyatakan pihaknya akan berkolaborasi dengan seluruh pihak untuk ...",
      "published": "2026-07-10T07:50:18+00:00",
      "source": "Antara News",
      "groups": [
        "Government / Policy"
      ],
      "matched": [
        "menteri"
      ],
      "big": false,
      "id": "b6eb73b868b80a5a"
    },
    {
      "title": "Pimpinan MPR: SRUK perlu didukung regulasi untuk perkuat pasar karbon",
      "link": "https://www.antaranews.com/berita/5643988/pimpinan-mpr-sruk-perlu-didukung-regulasi-untuk-perkuat-pasar-karbon",
      "summary": "Wakil Ketua MPR RI Eddy Soeparno menilai peluncuran Sistem Registri Unit Karbon (SRUK) menjadi langkah strategis ...",
      "published": "2026-07-10T07:42:01+00:00",
      "source": "Antara News",
      "groups": [
        "Government / Policy"
      ],
      "matched": [
        "MPR"
      ],
      "big": false,
      "id": "63938ac1e8dcf247"
    },
    {
      "title": "Menteri LH: Tenggat batas pemda tutup TPA \"open dumping\" tahun 2027",
      "link": "https://www.antaranews.com/berita/5643977/menteri-lh-tenggat-batas-pemda-tutup-tpa-open-dumping-tahun-2027",
      "summary": "Menteri Lingkungan Hidup (LH) Moh. Jumhur Hidayat menegaskan tenggat waktu batas pemerintah daerah (pemda) menutup ...",
      "published": "2026-07-10T07:37:54+00:00",
      "source": "Antara News",
      "groups": [
        "Government / Policy"
      ],
      "matched": [
        "menteri"
      ],
      "big": false,
      "id": "1db0f19f0a76039a"
    },
    {
      "title": "The US is building a new pressure architecture against Iran",
      "link": "https://www.aljazeera.com/opinions/2026/7/10/the-us-is-building-a-new-pressure-architecture-against-iran?traffic_source=rss",
      "summary": "Trump’s NATO diplomacy is part of a wider effort to weaken Tehran by reshaping the region around it.",
      "published": "2026-07-10T07:29:09+00:00",
      "source": "Al Jazeera",
      "groups": [
        "Geopolitics"
      ],
      "matched": [
        "Trump"
      ],
      "big": false,
      "id": "b372aae2eee830d9"
    },
    {
      "title": "South Korea’s SK Hynix raises $26.5bn in record-breaking US IPO",
      "link": "https://www.aljazeera.com/economy/2026/7/10/south-koreas-sk-hynix-raises-26-5bn-in-record-breaking-us-ipo?traffic_source=rss",
      "summary": "South Korean chip giant makes largest-ever debut by a foreign firm in the US, eclipsing Alibaba&#039;s 2014 IPO.",
      "published": "2026-07-10T07:02:05+00:00",
      "source": "Al Jazeera",
      "groups": [
        "Global Finance"
      ],
      "matched": [
        "IPO"
      ],
      "big": false,
      "id": "0ac4b1d157604207"
    },
    {
      "title": "Selandia Baru jajaki peluang gabung aliansi pertahanan Australia-Fiji",
      "link": "https://www.antaranews.com/berita/5643699/selandia-baru-jajaki-peluang-gabung-aliansi-pertahanan-australia-fiji",
      "summary": "Perdana Menteri (PM) Selandia Baru Christopher Luxon menyatakan bahwa pihaknya tengah menjajaki kemungkinan untuk ...",
      "published": "2026-07-10T05:03:44+00:00",
      "source": "Antara News",
      "groups": [
        "Government / Policy"
      ],
      "matched": [
        "menteri"
      ],
      "big": false,
      "id": "5dc13f0ef957c848"
    },
    {
      "title": "Seskab: Presiden Prabowo ke NTB untuk resmikan bendungan",
      "link": "https://www.antaranews.com/berita/5643687/seskab-presiden-prabowo-ke-ntb-untuk-resmikan-bendungan",
      "summary": "Presiden Prabowo Subianto bertolak menuju Provinsi Nusa Tenggara Barat (NTB), Jumat&nbsp;untuk meresmikan Bendungan ...",
      "published": "2026-07-10T04:44:46+00:00",
      "source": "Antara News",
      "groups": [
        "Government / Policy"
      ],
      "matched": [
        "Prabowo"
      ],
      "big": false,
      "id": "460890c28a3fe57d"
    },
    {
      "title": "Rupiah menguat seiring perkembangan positif antara AS dengan Iran",
      "link": "https://www.antaranews.com/berita/5643647/rupiah-menguat-seiring-perkembangan-positif-antara-as-dengan-iran",
      "summary": "Nilai tukar rupiah terhadap dolar AS pada Jumat pagi, bergerak menguat 63 poin atau 0,35 persen menjadi Rp18.065 per ...",
      "published": "2026-07-10T04:12:47+00:00",
      "source": "Antara News",
      "groups": [
        "Macro / Economy"
      ],
      "matched": [
        "rupiah"
      ],
      "big": true,
      "id": "e2e0500420c984ee"
    },
    {
      "title": "KPK periksa Bupati Sukoharjo usai terjaring OTT",
      "link": "https://www.antaranews.com/foto/5643644/kpk-periksa-bupati-sukoharjo-usai-terjaring-ott",
      "summary": "Petugas mengawal Bupati Sukoharjo Etik Suryani (kiri) saat tiba untuk menjalani pemeriksaan di Gedung Merah Putih KPK, ...",
      "published": "2026-07-10T04:10:47+00:00",
      "source": "Antara News",
      "groups": [
        "Government / Policy"
      ],
      "matched": [
        "KPK",
        "OTT"
      ],
      "big": false,
      "id": "085f3f1125843cd7"
    },
    {
      "title": "Menteri LH: Perusahaan pemilik konsesi wajib jaga lahan dari karhutla",
      "link": "https://www.antaranews.com/berita/5643641/menteri-lh-perusahaan-pemilik-konsesi-wajib-jaga-lahan-dari-karhutla",
      "summary": "Menteri Lingkungan Hidup (LH)/Kepala Badan Pengendalian Lingkungan Hidup (BPLH) Moh. Jumhur Hidayat menegaskan ...",
      "published": "2026-07-10T04:08:56+00:00",
      "source": "Antara News",
      "groups": [
        "Government / Policy"
      ],
      "matched": [
        "menteri"
      ],
      "big": false,
      "id": "948b1a405ff8f411"
    },
    {
      "title": "Bupati Sukoharjo Etik Suryani jalani pemeriksaan lanjutan di Jakarta",
      "link": "https://www.antaranews.com/berita/5643639/bupati-sukoharjo-etik-suryani-jalani-pemeriksaan-lanjutan-di-jakarta",
      "summary": "Bupati Sukoharjo Etik Suryani menjalani pemeriksaan lanjutan oleh Komisi Pemberantasan Korupsi (KPK) setelah tiba di ...",
      "published": "2026-07-10T04:08:44+00:00",
      "source": "Antara News",
      "groups": [
        "Government / Policy"
      ],
      "matched": [
        "KPK"
      ],
      "big": false,
      "id": "6d27c52a0334d8ce"
    },
    {
      "title": "Mentan ajak petani Lombok terapkan sistem pola tanam modern PMAAS",
      "link": "https://www.antaranews.com/berita/5643625/mentan-ajak-petani-lombok-terapkan-sistem-pola-tanam-modern-pmaas",
      "summary": "Menteri Pertanian (Mentan) Andi Amran Sulaiman mengajak petani Lombok, Nusa Tenggara Barat (NTB) untuk menerapkan ...",
      "published": "2026-07-10T04:05:53+00:00",
      "source": "Antara News",
      "groups": [
        "Government / Policy"
      ],
      "matched": [
        "menteri"
      ],
      "big": false,
      "id": "de9af4012aea7e15"
    },
    {
      "title": "Zelenskyy urges urgent efforts in Ukraine to start Patriot production",
      "link": "https://www.aljazeera.com/news/2026/7/10/zelenskyy-urges-urgent-efforts-in-ukraine-to-start-patriot-production?traffic_source=rss",
      "summary": "US President Donald Trump gave his blessing earlier this week to domestic Ukrainian production of the missiles.",
      "published": "2026-07-10T04:03:36+00:00",
      "source": "Al Jazeera",
      "groups": [
        "Geopolitics"
      ],
      "matched": [
        "Trump"
      ],
      "big": false,
      "id": "eef3a08ab4c4556b"
    },
    {
      "title": "Wamendiktisaintek dorong Konsorsium kampus entaskan kemiskinan di NTT",
      "link": "https://www.antaranews.com/berita/5643609/wamendiktisaintek-dorong-konsorsium-kampus-entaskan-kemiskinan-di-ntt",
      "summary": "Wakil Menteri Pendidikan Tinggi, Sains, dan Teknologi (Wamendiktisaintek) Prof. Dr. Fauzan mendesak perguruan tinggi di ...",
      "published": "2026-07-10T03:58:50+00:00",
      "source": "Antara News",
      "groups": [
        "Government / Policy"
      ],
      "matched": [
        "menteri"
      ],
      "big": false,
      "id": "bc02a7463d7e8f89"
    },
    {
      "title": "Pemkot Jaksel terapkan empat prinsip utama dalam pengelolaan anggaran",
      "link": "https://www.antaranews.com/berita/5643607/pemkot-jaksel-terapkan-empat-prinsip-utama-dalam-pengelolaan-anggaran",
      "summary": "Pemerintah Kota (Pemkot) Administrasi Jakarta Selatan (Jaksel) menerapkan empat prinsip utama dalam pengelolaan ...",
      "published": "2026-07-10T03:57:59+00:00",
      "source": "Antara News",
      "groups": [
        "Government / Policy"
      ],
      "matched": [
        "anggaran"
      ],
      "big": false,
      "id": "ca75fd399399af42"
    },
    {
      "title": "Menko Zulhas Kenang Rachmat Gobel sahabat dan pejuang bangsa",
      "link": "https://www.antaranews.com/berita/5643600/menko-zulhas-kenang-rachmat-gobel-sahabat-dan-pejuang-bangsa",
      "summary": "Menteri Koordinator Bidang Pangan Zulkifli Hasan (Zulhas) mengenang almarhum Anggota DPR RI Rachmat Gobel sebagai ...",
      "published": "2026-07-10T03:53:22+00:00",
      "source": "Antara News",
      "groups": [
        "Government / Policy"
      ],
      "matched": [
        "DPR",
        "menteri"
      ],
      "big": false,
      "id": "99d70a0f57a40d6b"
    },
    {
      "title": "Menekraf dorong hilirisasi kreativitas lewat IndoBuildTech Expo 2026",
      "link": "https://www.antaranews.com/berita/5643592/menekraf-dorong-hilirisasi-kreativitas-lewat-indobuildtech-expo-2026",
      "summary": "Menteri Ekonomi Kreatif (Menekraf) Teuku Riefky Harsya mengatakan&nbsp;IndoBuildTech Expo 2026 menjadi momentum ...",
      "published": "2026-07-10T03:39:56+00:00",
      "source": "Antara News",
      "groups": [
        "Commodity / Energy Policy",
        "Government / Policy"
      ],
      "matched": [
        "hilirisasi",
        "menteri"
      ],
      "big": false,
      "id": "e0e4fa9e3a721275"
    },
    {
      "title": "Menkop: Sekitar 30 ribu Koperasi Desa Merah Putih telah terbentuk",
      "link": "https://www.antaranews.com/berita/5643584/menkop-sekitar-30-ribu-koperasi-desa-merah-putih-telah-terbentuk",
      "summary": "Menteri Koperasi (Menkop) Ferry Juliantono mengatakan sekitar 30 ribu&nbsp;Koperasi Desa/Kelurahan Merah Putih (KDMP) ...",
      "published": "2026-07-10T03:27:19+00:00",
      "source": "Antara News",
      "groups": [
        "Government / Policy"
      ],
      "matched": [
        "menteri"
      ],
      "big": false,
      "id": "3eb34c23a7f768f7"
    },
    {
      "title": "IHSG menguat dipicu kombinasi sentimen global dan domestik",
      "link": "https://www.antaranews.com/berita/5643580/ihsg-menguat-dipicu-kombinasi-sentimen-global-dan-domestik",
      "summary": "Indeks Harga Saham Gabungan (IHSG) Bursa Efek Indonesia (BEI) pada Jumat pagi bergerak menguat dipicu oleh kombinasi ...",
      "published": "2026-07-10T03:24:07+00:00",
      "source": "Antara News",
      "groups": [
        "Macro / Economy"
      ],
      "matched": [
        "IHSG",
        "bursa efek Indonesia"
      ],
      "big": false,
      "id": "a27b2243592f9e77"
    },
    {
      "title": "Pengamat dorong evaluasi APBN fokus pada efektivitas belanja negara",
      "link": "https://www.antaranews.com/berita/5643573/pengamat-dorong-evaluasi-apbn-fokus-pada-efektivitas-belanja-negara",
      "summary": "Pengamat kebijakan publik Arfianto Purbolaksono mendorong evaluasi Anggaran Pendapatan dan Belanja Negara (APBN) tidak ...",
      "published": "2026-07-10T03:17:12+00:00",
      "source": "Antara News",
      "groups": [
        "Government / Policy"
      ],
      "matched": [
        "APBN",
        "anggaran"
      ],
      "big": true,
      "id": "c297c82bd53e2514"
    },
    {
      "title": "Strait of Hormuz traffic plunges as US, Iran resume fighting",
      "link": "https://www.aljazeera.com/economy/2026/7/10/strait-of-hormuz-shipping-grinds-to-halt-as-us-iran-resume-fighting?traffic_source=rss",
      "summary": "Brent crude holds steady despite a plunge in traffic in the critical waterway.",
      "published": "2026-07-10T02:55:59+00:00",
      "source": "Al Jazeera",
      "groups": [
        "Global Finance"
      ],
      "matched": [
        "Brent crude"
      ],
      "big": false,
      "id": "3c0cbe357dd8f58a"
    },
    {
      "title": "Chip giant SK Hynix raises $26.5bn in mega US share sale",
      "link": "https://www.bbc.co.uk/news/articles/c4gym70r0y4o?at_medium=RSS&at_campaign=rss",
      "summary": "The shares are set to start trading on the Nasdaq on Friday in what will be the largest ever debut by a foreign firm.",
      "published": "2026-07-10T02:48:18+00:00",
      "source": "BBC Business",
      "groups": [
        "Global Finance"
      ],
      "matched": [
        "Nasdaq"
      ],
      "big": false,
      "id": "7f151ce4d4a99605"
    },
    {
      "title": "How World Bank and IMF loans are reshaping policymaking in Africa",
      "link": "https://www.aljazeera.com/economy/2026/7/10/how-world-bank-and-imf-loans-are-reshaping-policymaking-in-africa?traffic_source=rss",
      "summary": "As debt pressures grow, African governments are reassessing the trade-offs of concessional financing.",
      "published": "2026-07-10T00:56:19+00:00",
      "source": "Al Jazeera",
      "groups": [
        "Global Finance"
      ],
      "matched": [
        "IMF",
        "World Bank"
      ],
      "big": false,
      "id": "8ca377ed58aa9391"
    },
    {
      "title": "KPK umumkan OTT Bupati Sukoharjo Etik Suryani terkait dugaan pemerasan",
      "link": "https://www.antaranews.com/berita/5643405/kpk-umumkan-ott-bupati-sukoharjo-etik-suryani-terkait-dugaan-pemerasan",
      "summary": "Komisi Pemberantasan Korupsi (KPK) mengumumkan operasi tangkap tangan (OTT) yang menangkap Bupati Sukoharjo Etik ...",
      "published": "2026-07-10T00:26:19+00:00",
      "source": "Antara News",
      "groups": [
        "Government / Policy"
      ],
      "matched": [
        "KPK",
        "OTT"
      ],
      "big": false,
      "id": "b371b2e6da0ac555"
    },
    {
      "title": "Menpar sebut sektor pariwisata tumbuh positif hingga bulan Mei 2026",
      "link": "https://www.antaranews.com/berita/5643404/menpar-sebut-sektor-pariwisata-tumbuh-positif-hingga-bulan-mei-2026",
      "summary": "Menteri Pariwisata Widiyanti Putri Wardhana menyebut sektor pariwisata Indonesia tetap tumbuh positif hingga bulan Mei ...",
      "published": "2026-07-10T00:25:22+00:00",
      "source": "Antara News",
      "groups": [
        "Government / Policy"
      ],
      "matched": [
        "menteri"
      ],
      "big": false,
      "id": "c50f437800bd9e4e"
    },
    {
      "title": "KPK tangkap empat orang selain Bupati Sukoharjo di wilayah Solo Raya",
      "link": "https://www.antaranews.com/berita/5643397/kpk-tangkap-empat-orang-selain-bupati-sukoharjo-di-wilayah-solo-raya",
      "summary": "Komisi Pemberantasan Korupsi (KPK) menangkap empat orang selain Bupati Sukoharjo Etik Suryani di wilayah Solo Raya, ...",
      "published": "2026-07-10T00:17:04+00:00",
      "source": "Antara News",
      "groups": [
        "Government / Policy"
      ],
      "matched": [
        "KPK"
      ],
      "big": false,
      "id": "59a46b99e169405a"
    },
    {
      "title": "Mentan: RI kehilangan putra terbaik bangsa atas wafatnya Rachmat Gobel",
      "link": "https://www.antaranews.com/berita/5643396/mentan-ri-kehilangan-putra-terbaik-bangsa-atas-wafatnya-rachmat-gobel",
      "summary": "Menteri Pertanian (Mentan) Andi Amran Sulaiman menyatakan Indonesia kehilangan putra terbaik bangsa atas wafatnya ...",
      "published": "2026-07-10T00:16:54+00:00",
      "source": "Antara News",
      "groups": [
        "Government / Policy"
      ],
      "matched": [
        "menteri"
      ],
      "big": false,
      "id": "e0ec21aff308f372"
    },
    {
      "title": "Pengguna jalan harap B50 dapat kurangi polusi dan harga lebih murah",
      "link": "https://www.antaranews.com/berita/5643391/pengguna-jalan-harap-b50-dapat-kurangi-polusi-dan-harga-lebih-murah",
      "summary": "Pengguna jalan berharap peluncuran program mandatori Biodiesel 50 (B50) oleh Presiden Prabowo di Rest Area KM 57, ...",
      "published": "2026-07-10T00:09:30+00:00",
      "source": "Antara News",
      "groups": [
        "Government / Policy"
      ],
      "matched": [
        "Prabowo"
      ],
      "big": false,
      "id": "ca013366f40affe8"
    },
    {
      "title": "China expands anti-sanctions toolkit, raising risks for foreign firms",
      "link": "https://www.aljazeera.com/news/2026/7/10/china-expands-anti-sanctions-toolkit-raising-risks-for-foreign-firms?traffic_source=rss",
      "summary": "Beijing is rolling out measures to expand its ability to hit back at US and EU sanctions and export controls.",
      "published": "2026-07-10T00:04:52+00:00",
      "source": "Al Jazeera",
      "groups": [
        "Global Finance"
      ],
      "matched": [
        "sanctions"
      ],
      "big": false,
      "id": "5f872534badf30ac"
    },
    {
      "title": "Anggota DPR RI Rachmat Gobel meninggal dunia",
      "link": "https://www.antaranews.com/berita/5643387/anggota-dpr-ri-rachmat-gobel-meninggal-dunia",
      "summary": "Anggota Dewan Perwakilan Rakyat Republik Indonesia (DPR RI) dan Menteri Perdagangan periode 2014-2015 Rachmat Gobel ...",
      "published": "2026-07-10T00:03:44+00:00",
      "source": "Antara News",
      "groups": [
        "Government / Policy"
      ],
      "matched": [
        "DPR",
        "menteri"
      ],
      "big": false,
      "id": "0d631e6bea39ad11"
    },
    {
      "title": "Prabowo’s Clampdown on Indonesian Tycoons Fuels Capital Flight - Bloomberg.com",
      "link": "https://news.google.com/rss/articles/CBMiywFBVV95cUxOalFscFpzY2tVX0VwSUxzNXdpUWgybHRhdzM4N3hxV0diMWVhY01tUENNaXdGM3Fsa0stYUI4RUFwcUpQTk9uMXBXb3d4cDZreXRINTIwQjR0YkJCY2xJdXBWTjJINkNXMnB2R3NBRGZmcGp5M2FvdkhBZzItZklYRGpZbW0tUWYxWVRiOXRVbWhxT2NlRFpHQ1JjV3hQcUtKWURoUE9BMkdUcFQ0M1lIT0dtSGZRTlBPZHQyVEZGUFk4LTU3VC1NRWZ6VQ?oc=5",
      "summary": "Prabowo’s Clampdown on Indonesian Tycoons Fuels Capital Flight&nbsp;&nbsp;Bloomberg.com",
      "published": "2026-07-10T00:00:00+00:00",
      "source": "Bloomberg (via GNews)",
      "groups": [
        "Financial Crisis Signals",
        "Government / Policy"
      ],
      "matched": [
        "Prabowo",
        "capital flight"
      ],
      "big": true,
      "id": "3ea755f3fb740c56"
    },
    {
      "title": "Petugas SPBU bangga jadi saksi peluncuran B50 oleh Prabowo",
      "link": "https://www.antaranews.com/berita/5643376/petugas-spbu-bangga-jadi-saksi-peluncuran-b50-oleh-prabowo",
      "summary": "Petugas SPBU Pertamina Tiara Rafalia Sari mengaku bangga menjadi saksi peluncuran B50 oleh Presiden Prabowo Subianto di ...",
      "published": "2026-07-09T23:54:09+00:00",
      "source": "Antara News",
      "groups": [
        "Commodity / Energy Policy",
        "Government / Policy"
      ],
      "matched": [
        "Pertamina",
        "Prabowo"
      ],
      "big": false,
      "id": "1c840605057f13af"
    },
    {
      "title": "Watch Can US Housing Relief Bill Survive Trump’s Power Play? - Bloomberg.com",
      "link": "https://news.google.com/rss/articles/CBMixwFBVV95cUxNSVZqOHpVLWM5QUp1VG1MVDVYVjUxNUVjb1hqeTJGRk5fWVJ4ZEF4NUhjMkNPZ3pwZF9IV01wcmlWNUJEdHJ0Uy11UVhQbzNZYlpnSjVmaDktQlE4N2Z4NkJUT01uRWpxNFUyUXkyYkczTWtXXzJqNl9tRG10X3g3VFQ0NURuaXhWVDBjdEllNnprVmJIbE1Wb1JFejlMU1otdVNWcm53VkNqcVdxMC04SmJ5XzZzNk1tY3Q3MTJidF9BQU9kSEFv?oc=5",
      "summary": "Watch Can US Housing Relief Bill Survive Trump’s Power Play?&nbsp;&nbsp;Bloomberg.com",
      "published": "2026-07-09T23:42:47+00:00",
      "source": "Bloomberg (via GNews)",
      "groups": [
        "Geopolitics"
      ],
      "matched": [
        "Trump"
      ],
      "big": false,
      "id": "7eae0469ddfa5f66"
    },
    {
      "title": "Beijing's acts dilute impact of South China Sea award, Manila's lawyer says - Nikkei Asia",
      "link": "https://news.google.com/rss/articles/CBMi4AFBVV95cUxOeU1iY3NQdkgzU1lMR2dKQ0ZvSldxSHctNGdqUmxKc0I5Rk9FZlNYNXloQ05RZ0tkRTBTTDlhRXFMalozQ1ZTMlczMW9Mem5BaHNqSkJadDVaVExnT3hkeC1FckdSN1Bxams5SDJCbzhRQm93UlhQVEZBOXNmTXJyanNCX2JwVml0OERaNmRBT2UtUmNkUUtqcTFOMFc4elF3RW1kYUZubnd0R3g3WjZQY0hmZklBT2lYUEVGZFVBWXBqVGJtR1FhMS1NYXZ0NVNDbzlkb2FWMDRnRzBiRm5EVg?oc=5",
      "summary": "Beijing's acts dilute impact of South China Sea award, Manila's lawyer says&nbsp;&nbsp;Nikkei Asia",
      "published": "2026-07-09T23:33:00+00:00",
      "source": "Nikkei Asia (via GNews)",
      "groups": [
        "Geopolitics"
      ],
      "matched": [
        "South China Sea"
      ],
      "big": false,
      "id": "9798412c7cf01839"
    },
    {
      "title": "New Mexico accuses US Justice Department of impeding Epstein investigation",
      "link": "https://www.aljazeera.com/news/2026/7/9/new-mexico-accuses-us-justice-department-of-impeding-epstein-investigation?traffic_source=rss",
      "summary": "State Attorney General Raul Torrez accused the Trump administration of withholding records, harming his investigation.",
      "published": "2026-07-09T23:25:48+00:00",
      "source": "Al Jazeera",
      "groups": [
        "Geopolitics"
      ],
      "matched": [
        "Trump"
      ],
      "big": false,
      "id": "3490247afb3a1dab"
    },
    {
      "title": "OTT ke-16, KPK tangkap Bupati Sukoharjo Etik Suryani",
      "link": "https://www.antaranews.com/berita/5643351/ott-ke-16-kpk-tangkap-bupati-sukoharjo-etik-suryani",
      "summary": "Komisi Pemberantasan Korupsi (KPK) melakukan operasi tangkap tangan (OTT) ke-16 pada 2026 dengan menangkap Bupati ...",
      "published": "2026-07-09T23:17:19+00:00",
      "source": "Antara News",
      "groups": [
        "Government / Policy"
      ],
      "matched": [
        "KPK",
        "OTT"
      ],
      "big": false,
      "id": "ba26c20858a819fe"
    },
    {
      "title": "BBPOM Semarang gencarkan edukasi keamanan produk bagi pelaku usaha",
      "link": "https://www.antaranews.com/video/5642949/bbpom-semarang-gencarkan-edukasi-keamanan-produk-bagi-pelaku-usaha",
      "summary": "ANTARA - Balai Besar Pengawas Obat dan Makanan (BBPOM) di Semarang bersama Komisi IX DPR RI menggelar edukasi keamanan ...",
      "published": "2026-07-09T22:43:55+00:00",
      "source": "Antara News",
      "groups": [
        "Government / Policy"
      ],
      "matched": [
        "DPR"
      ],
      "big": false,
      "id": "cd0b97d3972e0d5a"
    },
    {
      "title": "Komisi VII DPR dorong penguatan storytelling dan ekraf di desa wisata",
      "link": "https://www.antaranews.com/berita/5643331/komisi-vii-dpr-dorong-penguatan-storytelling-dan-ekraf-di-desa-wisata",
      "summary": "Komisi VII DPR RI mendorong penguatan konsep storytelling&nbsp;atau penyampaian pesan melalui cerita dan pengembangan ...",
      "published": "2026-07-09T22:43:54+00:00",
      "source": "Antara News",
      "groups": [
        "Government / Policy"
      ],
      "matched": [
        "DPR"
      ],
      "big": false,
      "id": "187a9ea3eeb06c76"
    },
    {
      "title": "Trump airport name change sparks backlash  in Florida",
      "link": "https://www.aljazeera.com/video/newsfeed/2026/7/9/trump-airport-name-change-sparks-backlash-in-florida?traffic_source=rss",
      "summary": "Trump airport name change sparks backlash  in Florida",
      "published": "2026-07-09T21:26:34+00:00",
      "source": "Al Jazeera",
      "groups": [
        "Geopolitics"
      ],
      "matched": [
        "Trump"
      ],
      "big": false,
      "id": "47b34eb24a92e418"
    },
    {
      "title": "Most Emerging Market Currencies Rebound Amid ‘Headline Fatigue’ - Bloomberg.com",
      "link": "https://news.google.com/rss/articles/CBMisgFBVV95cUxNTmpZT1FTci1aUFVFOEdfX1Zmb2V6YlhzeW54elkzdzlOTTVqOU1pRGRKdHBiRjhMVTdCMEJydm9NVWZVc0djWVFmYTUwSlk5WEQ2M214YXpJbVNmcGZteDV4NzhkNkFfZjBFNGVEdndUbDRMbzFha1R5d0cyMDBRd2tqWEI4UDVVOVNJN0FFa3hGQmdnUV94YUNSMllZeU9lMUp5RHFyUzVjVDRHcTQ2N1ZR?oc=5",
      "summary": "Most Emerging Market Currencies Rebound Amid ‘Headline Fatigue’&nbsp;&nbsp;Bloomberg.com",
      "published": "2026-07-09T20:52:08+00:00",
      "source": "Bloomberg (via GNews)",
      "groups": [
        "Global Finance"
      ],
      "matched": [
        "emerging market"
      ],
      "big": false,
      "id": "d038cb8ca6bad42c"
    },
    {
      "title": "UK Labour’s Burnham apologises for response to Israel’s Gaza violence",
      "link": "https://www.aljazeera.com/news/2026/7/9/uk-labours-burnham-apologises-for-response-to-israels-gaza-violence?traffic_source=rss",
      "summary": "UK&#039;s likely next PM Burnham pushes for ceasefire, tougher sanctions over Gaza violence and settlement trade bans.",
      "published": "2026-07-09T20:20:39+00:00",
      "source": "Al Jazeera",
      "groups": [
        "Global Finance"
      ],
      "matched": [
        "sanctions"
      ],
      "big": false,
      "id": "e689e195d3001060"
    },
    {
      "title": "Is Syria stable enough to engage with the world?",
      "link": "https://www.aljazeera.com/video/inside-story/2026/7/9/is-syria-stable-enough-to-engage-with-the-world?traffic_source=rss",
      "summary": "The Trump administration plans to remove Syria from list of state sponsors of &#039;terrorism&#039;.",
      "published": "2026-07-09T18:56:46+00:00",
      "source": "Al Jazeera",
      "groups": [
        "Geopolitics"
      ],
      "matched": [
        "Trump"
      ],
      "big": false,
      "id": "1def62bdae93963a"
    },
    {
      "title": "Yusril minta perpres pertahanan tak ditafsirkan untuk persekusi",
      "link": "https://www.antaranews.com/video/5643237/yusril-minta-perpres-pertahanan-tak-ditafsirkan-untuk-persekusi",
      "summary": "ANTARA - Menteri Koordinator Bidang Hukum, HAM, Imigrasi, dan Pemasyarakatan Yusril Ihza Mahendra menegaskan Peraturan ...",
      "published": "2026-07-09T18:15:39+00:00",
      "source": "Antara News",
      "groups": [
        "Government / Policy"
      ],
      "matched": [
        "menteri"
      ],
      "big": false,
      "id": "a1290d42dc8f1e79"
    },
    {
      "title": "Arab Saudi apresiasi sinergi Indonesia sukseskan pelaksanaan haji 2026",
      "link": "https://www.antaranews.com/berita/5643251/arab-saudi-apresiasi-sinergi-indonesia-sukseskan-pelaksanaan-haji-2026",
      "summary": "Kedutaan Besar Arab Saudi di Jakarta dan maskapai penerbangan Kerajaan Arab Saudi, Saudia Airlines, memperkuat ...",
      "published": "2026-07-09T18:05:44+00:00",
      "source": "Antara News",
      "groups": [
        "Macro / Economy"
      ],
      "matched": [
        "apresiasi"
      ],
      "big": false,
      "id": "66392d163328c93d"
    },
    {
      "title": "Interest rates may need to rise this year, says Bank of England economist",
      "link": "https://www.bbc.co.uk/news/articles/c932ed8nv75o?at_medium=RSS&at_campaign=rss",
      "summary": "Chief economist at the Bank of England says slower growth and inflationary pressures mean rate rise needed",
      "published": "2026-07-09T17:37:11+00:00",
      "source": "BBC Business",
      "groups": [
        "Global Finance"
      ],
      "matched": [
        "Bank of England",
        "interest rate"
      ],
      "big": false,
      "id": "3f016db1a607d755"
    },
    {
      "title": "Komisi X DPR targetkan RUU Sisdiknas rampung pada 2027",
      "link": "https://www.antaranews.com/berita/5643227/komisi-x-dpr-targetkan-ruu-sisdiknas-rampung-pada-2027",
      "summary": "Komisi X DPR RI menargetkan Rancangan Undang-Undang tentang Sistem Pendidikan Nasional atau&nbsp;Sisdiknas&nbsp;dapat ...",
      "published": "2026-07-09T17:10:21+00:00",
      "source": "Antara News",
      "groups": [
        "Government / Policy"
      ],
      "matched": [
        "DPR",
        "UU "
      ],
      "big": false,
      "id": "1b83d5f556e0a39d"
    },
    {
      "title": "Komisi VII DPR dorong transformasi Pekan Raya Sumut",
      "link": "https://www.antaranews.com/video/5643185/komisi-vii-dpr-dorong-transformasi-pekan-raya-sumut",
      "summary": "ANTARA - Komisi VII DPR RI mendorong Pekan Raya Sumatera Utara (PRSU) bertransformasi menjadi ajang perdagangan, ...",
      "published": "2026-07-09T16:54:04+00:00",
      "source": "Antara News",
      "groups": [
        "Government / Policy"
      ],
      "matched": [
        "DPR"
      ],
      "big": false,
      "id": "36eebf62a0ea754f"
    },
    {
      "title": "KPK tahan eks Sekjen MPR dalam kasus dugaan gratifikasi",
      "link": "https://www.antaranews.com/video/5643103/kpk-tahan-eks-sekjen-mpr-dalam-kasus-dugaan-gratifikasi",
      "summary": "ANTARA - Mantan Sekretaris Jenderal MPR RI Ma&rsquo;ruf Cahyono resmi ditangkap Komisi Pemberantasan Korupsi (KPK) di ...",
      "published": "2026-07-09T16:43:50+00:00",
      "source": "Antara News",
      "groups": [
        "Government / Policy"
      ],
      "matched": [
        "KPK",
        "MPR"
      ],
      "big": false,
      "id": "c94ac6f1db9f3f8f"
    },
    {
      "title": "Kompolnas dukung Polri usut tuntas kasus dugaan korupsi batu bara",
      "link": "https://www.antaranews.com/berita/5643201/kompolnas-dukung-polri-usut-tuntas-kasus-dugaan-korupsi-batu-bara",
      "summary": "Anggota Komisi Kepolisian Nasional (Kompolnas) Mohammad Choirul Anam menyatakan dukungannya kepada pihak kepolisian ...",
      "published": "2026-07-09T16:38:02+00:00",
      "source": "Antara News",
      "groups": [
        "Commodity / Energy Policy"
      ],
      "matched": [
        "batu bara"
      ],
      "big": false,
      "id": "afe46156904b3885"
    },
    {
      "title": "Presiden minta upaya maksimal wujudkan mimpi Timnas tembus Piala Dunia",
      "link": "https://www.antaranews.com/video/5643180/presiden-minta-upaya-maksimal-wujudkan-mimpi-timnas-tembus-piala-dunia",
      "summary": "ANTARA - Presiden Prabowo Subianto menyampaikan harapannya agar Tim Nasional Indonesia mampu menembus Piala Dunia saat ...",
      "published": "2026-07-09T16:37:33+00:00",
      "source": "Antara News",
      "groups": [
        "Government / Policy"
      ],
      "matched": [
        "Prabowo"
      ],
      "big": false,
      "id": "a77fe526fd493d58"
    },
    {
      "title": "Gubernur Sumut mendukung PRSU masuk Karisma Event Nusantara",
      "link": "https://www.antaranews.com/berita/5643199/gubernur-sumut-mendukung-prsu-masuk-karisma-event-nusantara",
      "summary": "Gubernur Sumatera Utara (Sumut) Bobby Nasution mendukung niat Komisi VII DPR RI agar Pekan Raya Sumatera Utara (PRSU) ...",
      "published": "2026-07-09T16:37:19+00:00",
      "source": "Antara News",
      "groups": [
        "Government / Policy"
      ],
      "matched": [
        "DPR"
      ],
      "big": false,
      "id": "52494baf04a6c954"
    },
    {
      "title": "Sopir truk merasakan manfaat B50, mesin lebih bertenaga",
      "link": "https://www.antaranews.com/berita/5643188/sopir-truk-merasakan-manfaat-b50-mesin-lebih-bertenaga",
      "summary": "Peluncuran kebijakan Mandatori Biodiesel B50 oleh Presiden Prabowo Subianto dirasakan manfaatnya oleh para sopir truk, ...",
      "published": "2026-07-09T16:28:50+00:00",
      "source": "Antara News",
      "groups": [
        "Government / Policy"
      ],
      "matched": [
        "Prabowo"
      ],
      "big": false,
      "id": "db091fb53d7c336a"
    },
    {
      "title": "Kolaborasi dirgantara hingga kereta api disasar dalam SIBS@ASEAN 2026",
      "link": "https://www.antaranews.com/berita/5643176/kolaborasi-dirgantara-hingga-kereta-api-disasar-dalam-sibsasean-2026",
      "summary": "Pemerintah Provinsi (Pemprov) Jawa Barat (Jabar) dan Pemerintah Negara Bagian Selangor, Malaysia, menyasar kolaborasi ...",
      "published": "2026-07-09T16:22:13+00:00",
      "source": "Antara News",
      "groups": [
        "Geopolitics"
      ],
      "matched": [
        "ASEAN"
      ],
      "big": false,
      "id": "56e8d39fd43b360d"
    },
    {
      "title": "Prabowo tukar pikiran dengan tiga eks PM Thailand di Wisma Danantara",
      "link": "https://www.antaranews.com/berita/5643167/prabowo-tukar-pikiran-dengan-tiga-eks-pm-thailand-di-wisma-danantara",
      "summary": "Presiden Prabowo Subianto bertukar pikiran dengan tiga mantan Perdana Menteri (PM) Thailand&nbsp;di Wisma Danantara, ...",
      "published": "2026-07-09T16:11:47+00:00",
      "source": "Antara News",
      "groups": [
        "Government / Policy"
      ],
      "matched": [
        "Prabowo",
        "menteri"
      ],
      "big": false,
      "id": "1e03f65b3c004ebd"
    },
    {
      "title": "Mendagri dukung integrasi data lewat RUU kebijakan Satu Data Indonesia",
      "link": "https://www.antaranews.com/video/5643145/mendagri-dukung-integrasi-data-lewat-ruu-kebijakan-satu-data-indonesia",
      "summary": "ANTARA -&nbsp;Kementerian Dalam Negeri mendukung Rancangan Undang-Undang (RUU) Satu Data Indonesia untuk pengelolaan ...",
      "published": "2026-07-09T16:08:48+00:00",
      "source": "Antara News",
      "groups": [
        "Government / Policy"
      ],
      "matched": [
        "UU "
      ],
      "big": false,
      "id": "74539948321da20d"
    },
    {
      "title": "Bandara Palm Beach resmi berganti nama jadi Donald J.Trump",
      "link": "https://www.antaranews.com/berita/5643164/bandara-palm-beach-resmi-berganti-nama-jadi-donald-jtrump",
      "summary": "Bandara Internasional Palm Beach di Florida telah resmi berganti nama untuk menghormati Presiden AS Donald Trump, ...",
      "published": "2026-07-09T16:07:13+00:00",
      "source": "Antara News",
      "groups": [
        "Geopolitics"
      ],
      "matched": [
        "Trump"
      ],
      "big": false,
      "id": "1b22c6ffa172d82d"
    },
    {
      "title": "Former US Olympian pleads not guilty in DC reflecting pool vandalism case",
      "link": "https://www.aljazeera.com/news/2026/7/9/former-us-olympian-pleads-not-guilty-in-dc-reflecting-pool-vandalism-case?traffic_source=rss",
      "summary": "Former Olympic canoeist David Hearn denies damaging Donald Trump’s Washington, DC reflecting pool renovation.",
      "published": "2026-07-09T16:06:18+00:00",
      "source": "Al Jazeera",
      "groups": [
        "Geopolitics"
      ],
      "matched": [
        "Trump"
      ],
      "big": false,
      "id": "e762ea45e3358840"
    },
    {
      "title": "Watch Trump Stops in UK to Switch Air Force One Planes - Bloomberg.com",
      "link": "https://news.google.com/rss/articles/CBMipgFBVV95cUxQSVBmUGIxa1I4YmM0WXlNU0RmXzRGWjdzV1BTeVZZYzN5d0J3T2pHOG5hYW5YRWZyZ1gxT0FyV0FmT0ZNdHUzdlRNVjFqbU9zZWNsRlFqZnpfVWZRX3RPdmFvZEY4UV9tTlN6RC1adnVoZXVPRnc2dEx4UElBeEV4T2ZicXBMRVpZcHFmVWxCSUxucXZzUG5mbWs2NjRxWmtiUzZ6dUdB?oc=5",
      "summary": "Watch Trump Stops in UK to Switch Air Force One Planes&nbsp;&nbsp;Bloomberg.com",
      "published": "2026-07-09T15:58:57+00:00",
      "source": "Bloomberg (via GNews)",
      "groups": [
        "Geopolitics"
      ],
      "matched": [
        "Trump"
      ],
      "big": false,
      "id": "cd5dc946b3dddf6f"
    },
    {
      "title": "Menkes: \"Makan Dengan Makna\" ajak gen Z manfaatkan pangan lokal",
      "link": "https://www.antaranews.com/berita/5643132/menkes-makan-dengan-makna-ajak-gen-z-manfaatkan-pangan-lokal",
      "summary": "Menteri Kesehatan Budi Gunadi Sadikin mengatakan, melalui inisiatif &quot;Makan Dengan Makna&quot;, pihaknya mengajak ...",
      "published": "2026-07-09T15:43:31+00:00",
      "source": "Antara News",
      "groups": [
        "Government / Policy"
      ],
      "matched": [
        "menteri"
      ],
      "big": false,
      "id": "77bf795eaa282b32"
    },
    {
      "title": "Presiden Prabowo ingatkan para pimpinan soal \"inferiority complex\"",
      "link": "https://www.antaranews.com/video/5643071/presiden-prabowo-ingatkan-para-pimpinan-soal-inferiority-complex",
      "summary": "ANTARA - Presiden Prabowo Subianto mengingatkan para pemimpin agar mawas diri terkait kekurangan yang mungkin ada dalam ...",
      "published": "2026-07-09T15:38:00+00:00",
      "source": "Antara News",
      "groups": [
        "Government / Policy"
      ],
      "matched": [
        "Prabowo"
      ],
      "big": false,
      "id": "a07cae1c860c6fef"
    },
    {
      "title": "Prabowo ungkap rencana resmikan Bendungan Meninting di NTB pada Jumat",
      "link": "https://www.antaranews.com/berita/5643124/prabowo-ungkap-rencana-resmikan-bendungan-meninting-di-ntb-pada-jumat",
      "summary": "Presiden Prabowo Subianto mengungkap rencana kunjungan kerjanya meresmikan sekaligus meninjau secara langsung Bendungan ...",
      "published": "2026-07-09T15:33:35+00:00",
      "source": "Antara News",
      "groups": [
        "Government / Policy"
      ],
      "matched": [
        "Prabowo"
      ],
      "big": false,
      "id": "6a12d606092444f3"
    },
    {
      "title": "How One of the World’s Largest Publicly-Traded Hedge Funds Is Using AI - Bloomberg.com",
      "link": "https://news.google.com/rss/articles/CBMixwFBVV95cUxNVTZFNUJ1MjZqRm80eGRDSmxQMC1Ucy1fTzdTNVVXQVQxMzRsNDV5TnJndjdFQm55TTdjWE85NmViLWROR0VNU1p4cjdrNnRfZVFoekFRSndvQVB0eFlNWU1aakYwTnNrX2M1MllEeVVLX2FBTE1VTi16eG1XNGpGT2hob1FyWUFPX3IxN3dGc2MzajBvUGdSTlBDV0s0OXZvc3Z2ZmwzaGhoR0pxYTNXT2dsM1hMaGo1aHF3NW5tRm1obW0td1B3?oc=5",
      "summary": "How One of the World’s Largest Publicly-Traded Hedge Funds Is Using AI&nbsp;&nbsp;Bloomberg.com",
      "published": "2026-07-09T14:46:12+00:00",
      "source": "Bloomberg (via GNews)",
      "groups": [
        "Global Finance"
      ],
      "matched": [
        "hedge fund"
      ],
      "big": false,
      "id": "41686c093b0e0cf7"
    },
    {
      "title": "Prabowo minta riset biodiesel tak berhenti di B50",
      "link": "https://www.antaranews.com/berita/5642900/prabowo-minta-riset-biodiesel-tak-berhenti-di-b50",
      "summary": "Presiden Prabowo Subianto meminta para ilmuwan dan perguruan tinggi terus mengembangkan riset di sektor energi ...",
      "published": "2026-07-09T13:35:04+00:00",
      "source": "Antara News",
      "groups": [
        "Government / Policy"
      ],
      "matched": [
        "Prabowo"
      ],
      "big": false,
      "id": "cee154f7661d8c18"
    },
    {
      "title": "Menteri UMKM dorong perusahaan besar bina wirausaha baru",
      "link": "https://www.antaranews.com/berita/5642892/menteri-umkm-dorong-perusahaan-besar-bina-wirausaha-baru",
      "summary": "Menteri Usaha Mikro Kecil Menengah (UMKM) Maman Abdurrahman mendorong perusahaan-perusahaan besar memperluas program ...",
      "published": "2026-07-09T13:28:51+00:00",
      "source": "Antara News",
      "groups": [
        "Government / Policy"
      ],
      "matched": [
        "menteri"
      ],
      "big": false,
      "id": "87fae73b091dcb71"
    },
    {
      "title": "Menlu: RI perkuat multilateralisme, perluas ruang strategis",
      "link": "https://www.antaranews.com/berita/5642889/menlu-ri-perkuat-multilateralisme-perluas-ruang-strategis",
      "summary": "Menteri Luar Negeri Republik Indonesia Sugiono menegaskan bahwa Indonesia akan terus memperkuat multilateralisme agar ...",
      "published": "2026-07-09T13:28:10+00:00",
      "source": "Antara News",
      "groups": [
        "Government / Policy"
      ],
      "matched": [
        "menteri"
      ],
      "big": false,
      "id": "4621bdaa6bab73f4"
    },
    {
      "title": "Selangor siap jadi pintu masuk untuk ekspansi usaha Indonesia ke ASEAN",
      "link": "https://www.antaranews.com/berita/5642875/selangor-siap-jadi-pintu-masuk-untuk-ekspansi-usaha-indonesia-ke-asean",
      "summary": "Menteri Besar Selangor, Malaysia, YAB Dato&rsquo; Seri Amirudin bin Shari menyatakan negara bagian Selangor siap ...",
      "published": "2026-07-09T13:16:39+00:00",
      "source": "Antara News",
      "groups": [
        "Geopolitics",
        "Government / Policy"
      ],
      "matched": [
        "ASEAN",
        "menteri"
      ],
      "big": false,
      "id": "e90a3824574aaa89"
    },
    {
      "title": "Menhut: Perhutanan sosial dan hutan adat bisa ikut perdagangan karbon",
      "link": "https://www.antaranews.com/berita/5642872/menhut-perhutanan-sosial-dan-hutan-adat-bisa-ikut-perdagangan-karbon",
      "summary": "Menteri Kehutanan (Menhut) Raja Juli Antoni menegaskan perdagangan karbon sektor kehutanan kini tidak hanya ...",
      "published": "2026-07-09T13:15:52+00:00",
      "source": "Antara News",
      "groups": [
        "Government / Policy"
      ],
      "matched": [
        "menteri"
      ],
      "big": false,
      "id": "64f0699e212f511b"
    },
    {
      "title": "Riset Undana harus berdampak bagi penyelesaian masalah daerah",
      "link": "https://www.antaranews.com/berita/5642865/riset-undana-harus-berdampak-bagi-penyelesaian-masalah-daerah",
      "summary": "Wakil Menteri Pendidikan Tinggi, Sains, dan Teknologi (Wamendiktisaintek)&nbsp;Fauzan menilai Universitas Nusa Cendana ...",
      "published": "2026-07-09T13:10:31+00:00",
      "source": "Antara News",
      "groups": [
        "Government / Policy"
      ],
      "matched": [
        "menteri"
      ],
      "big": false,
      "id": "3dc7be04b9dd5189"
    },
    {
      "title": "Trump targets Spain, NATO backs Ukraine: Is the alliance still united?",
      "link": "https://www.aljazeera.com/news/2026/7/9/trump-targets-spain-nato-backs-ukraine-is-the-alliance-still-united?traffic_source=rss",
      "summary": "While NATO members have agreed to boost defence spending, Trump&#039;s attacks on Spain and Greenland have threatened unity.",
      "published": "2026-07-09T13:02:47+00:00",
      "source": "Al Jazeera",
      "groups": [
        "Geopolitics"
      ],
      "matched": [
        "Trump"
      ],
      "big": false,
      "id": "3b12daf3a755c9fd"
    },
    {
      "title": "KPK sebut Ma'ruf Cahyono pakai uang gratifikasi untuk nikahkan anak",
      "link": "https://www.antaranews.com/berita/5642859/kpk-sebut-maruf-cahyono-pakai-uang-gratifikasi-untuk-nikahkan-anak",
      "summary": "Komisi Pemberantasan Korupsi (KPK) menyebut mantan Sekretaris Jenderal MPR RI Ma'ruf Cahyono diduga menggunakan ...",
      "published": "2026-07-09T13:01:11+00:00",
      "source": "Antara News",
      "groups": [
        "Government / Policy"
      ],
      "matched": [
        "KPK",
        "MPR"
      ],
      "big": false,
      "id": "88e94d47e20a32e2"
    },
    {
      "title": "Indonesia pelopor penerapan B50",
      "link": "https://www.antaranews.com/infografik/5642835/indonesia-pelopor-penerapan-b50",
      "summary": "Penerapan campuran solar dan minyak sawit atau biodiesel 50 persen (B50) diresmikan Presiden Prabowo Subianto, Kamis ...",
      "published": "2026-07-09T13:00:00+00:00",
      "source": "Antara News",
      "groups": [
        "Commodity / Energy Policy",
        "Government / Policy"
      ],
      "matched": [
        "Prabowo",
        "sawit"
      ],
      "big": false,
      "id": "6b57bf22ba4f90aa"
    },
    {
      "title": "Menko Yusril tegaskan Perpres 111/2025 bukan regulasi khusus LGBTQ",
      "link": "https://www.antaranews.com/berita/5642844/menko-yusril-tegaskan-perpres-111-2025-bukan-regulasi-khusus-lgbtq",
      "summary": "Menteri Koordinator Bidang Hukum, Hak Asasi Manusia, Imigrasi, dan Pemasyarakatan Yusril Ihza Mahendra menegaskan ...",
      "published": "2026-07-09T12:55:44+00:00",
      "source": "Antara News",
      "groups": [
        "Government / Policy"
      ],
      "matched": [
        "menteri"
      ],
      "big": false,
      "id": "bb6f8dae5e142cc1"
    },
    {
      "title": "Watch Legado de Fujimori desafía ofensiva anti-China de Trump en Perú - Bloomberg.com",
      "link": "https://news.google.com/rss/articles/CBMisgFBVV95cUxOdnVCQ0Z3dEh5b00tTjZXeXlMMmF0Q3pZQTNuZWJlMndGR29QbkdUT0M2N3p5OGI4NlcwMmpuN001SWpZakpxUDIwd05ZeWZPZm1qY29BM3VaOE5qSGh6NjBLZC1keFFjemFIWlpKaVRGU28wQnRGampGVkY1Q0VWb2o1V1pFVmdkVnBZUXVIenl5LWxvZEk5QTEyTjBJMlNaNU1ZV1pfck5QTFZ1cWU4dHhR?oc=5",
      "summary": "Watch Legado de Fujimori desafía ofensiva anti-China de Trump en Perú&nbsp;&nbsp;Bloomberg.com",
      "published": "2026-07-09T12:53:23+00:00",
      "source": "Bloomberg (via GNews)",
      "groups": [
        "Geopolitics"
      ],
      "matched": [
        "Trump"
      ],
      "big": false,
      "id": "d13369f8bac88517"
    },
    {
      "title": "Prabowo: Negara hemat devisa Rp170 triliun dari B50",
      "link": "https://www.antaranews.com/berita/5642833/prabowo-negara-hemat-devisa-rp170-triliun-dari-b50",
      "summary": "Presiden Prabowo Subianto mengatakan penerapan mandatori biodiesel B50 akan memberikan dampak besar bagi penguatan ...",
      "published": "2026-07-09T12:50:46+00:00",
      "source": "Antara News",
      "groups": [
        "Government / Policy"
      ],
      "matched": [
        "Prabowo"
      ],
      "big": false,
      "id": "dcd2f8e3e491523d"
    },
    {
      "title": "Pertamina Pride keluar Selat Hormuz, Kemlu: Bukti situasi membaik",
      "link": "https://www.antaranews.com/berita/5642829/pertamina-pride-keluar-selat-hormuz-kemlu-bukti-situasi-membaik",
      "summary": "Kementerian Luar Negeri (Kemlu) RI menyatakan bahwa keberhasilan&nbsp;kapal tanker very large crude carrier (VLCC) ...",
      "published": "2026-07-09T12:50:20+00:00",
      "source": "Antara News",
      "groups": [
        "Commodity / Energy Policy"
      ],
      "matched": [
        "Pertamina"
      ],
      "big": false,
      "id": "67005bd6701b7410"
    },
    {
      "title": "Bawaslu kaji penguatan kewenangan pascaputusan MK Nomor 135",
      "link": "https://www.antaranews.com/berita/5642799/bawaslu-kaji-penguatan-kewenangan-pascaputusan-mk-nomor-135",
      "summary": "Anggota Badan Pengawas Pemilihan Umum (Bawaslu) RI Puadi&nbsp;mengatakan lembaganya sedang mengkaji penguatan ...",
      "published": "2026-07-09T12:33:19+00:00",
      "source": "Antara News",
      "groups": [
        "Government / Policy"
      ],
      "matched": [
        "MK"
      ],
      "big": false,
      "id": "5d51abc93ea316e8"
    },
    {
      "title": "Menteri Bahlil sebut 57 persen SPBU sudah salurkan B50",
      "link": "https://www.antaranews.com/berita/5642795/menteri-bahlil-sebut-57-persen-spbu-sudah-salurkan-b50",
      "summary": "Menteri Energi dan Sumber Daya Mineral (ESDM) Bahlil Lahadalia menyampaikan sebanyak 57,6 persen stasiun pengisian ...",
      "published": "2026-07-09T12:32:55+00:00",
      "source": "Antara News",
      "groups": [
        "Government / Policy"
      ],
      "matched": [
        "menteri"
      ],
      "big": false,
      "id": "dfb3915d4bcdc95c"
    },
    {
      "title": "Pertamina Minta Bantuan Depot Siak Penuhi Pasokan BBM Sumbar",
      "link": "https://www.antaranews.com/video/5642728/pertamina-minta-bantuan-depot-siak-penuhi-pasokan-bbm-sumbar",
      "summary": "ANTARA - Pertamina Patra Niaga Sumatera Bagian Utara (Sumbagut) menyampaikan permohonan maaf atas kendala ...",
      "published": "2026-07-09T12:30:41+00:00",
      "source": "Antara News",
      "groups": [
        "Commodity / Energy Policy"
      ],
      "matched": [
        "Pertamina"
      ],
      "big": false,
      "id": "f9651dce0cf4977c"
    },
    {
      "title": "MPR: Sensus Ekonomi momentum dapatkan data untuk ekonomi inklusif",
      "link": "https://www.antaranews.com/berita/5642792/mpr-sensus-ekonomi-momentum-dapatkan-data-untuk-ekonomi-inklusif",
      "summary": "Wakil Ketua MPR RI Lestari Moerdijat mengatakan Sensus Ekonomi 2026 merupakan momentum mendapatkan data yang rinci dan ...",
      "published": "2026-07-09T12:29:43+00:00",
      "source": "Antara News",
      "groups": [
        "Government / Policy"
      ],
      "matched": [
        "MPR"
      ],
      "big": false,
      "id": "b3f1888983617e1b"
    },
    {
      "title": "Pemprov Jabar tawarkan enam proyek strategis pada SIBS 2026",
      "link": "https://www.antaranews.com/berita/5642785/pemprov-jabar-tawarkan-enam-proyek-strategis-pada-sibs-2026",
      "summary": "Pemerintah Provinsi Jawa Barat menawarkan enam proyek strategis kepada investor Malaysia dan negara-negara ASEAN pada ...",
      "published": "2026-07-09T12:27:02+00:00",
      "source": "Antara News",
      "groups": [
        "Geopolitics"
      ],
      "matched": [
        "ASEAN"
      ],
      "big": false,
      "id": "6207ee739ef38c42"
    },
    {
      "title": "KPK duga Ma'ruf Cahyono terima gratifikasi Rp37,8 M dari vendor Setjen MPR",
      "link": "https://www.antaranews.com/berita/5642780/kpk-duga-maruf-cahyono-terima-gratifikasi-rp378-m-dari-vendor-setjen-mpr",
      "summary": "Komisi Pemberantasan Korupsi (KPK) menduga Ma&rsquo;ruf Cahyono (MC) selama menjabat Sekretaris Jenderal MPR RI ...",
      "published": "2026-07-09T12:25:46+00:00",
      "source": "Antara News",
      "groups": [
        "Government / Policy"
      ],
      "matched": [
        "KPK",
        "MPR"
      ],
      "big": false,
      "id": "70876befb3afc294"
    },
    {
      "title": "Prabowo sampaikan duka atas gugurnya tiga polisi di Kalteng",
      "link": "https://www.antaranews.com/berita/5642504/prabowo-sampaikan-duka-atas-gugurnya-tiga-polisi-di-kalteng",
      "summary": "Presiden Prabowo Subianto menyampaikan belasungkawa atas gugurnya tiga anggota Polri saat mengungkap kasus narkotika di ...",
      "published": "2026-07-09T10:35:22+00:00",
      "source": "Antara News",
      "groups": [
        "Government / Policy"
      ],
      "matched": [
        "Prabowo"
      ],
      "big": false,
      "id": "9e2820092574c0fa"
    },
    {
      "title": "Megawati dan Xanana Gusmao siapkan kursus kaderisasi lintas negara",
      "link": "https://www.antaranews.com/berita/5642503/megawati-dan-xanana-gusmao-siapkan-kursus-kaderisasi-lintas-negara",
      "summary": "Presiden Ke-5 RI&nbsp;Megawati Soekarnoputri, dalam sesi konferensi pers bersama Perdana Menteri Timor Leste Kay Rala ...",
      "published": "2026-07-09T10:35:16+00:00",
      "source": "Antara News",
      "groups": [
        "Government / Policy"
      ],
      "matched": [
        "menteri"
      ],
      "big": false,
      "id": "3dab5b5ee47cb616"
    },
    {
      "title": "Said Iqbal temui Menaker bahas pekerja outsourcing hingga pajak JHT",
      "link": "https://www.antaranews.com/berita/5642499/said-iqbal-temui-menaker-bahas-pekerja-outsourcing-hingga-pajak-jht",
      "summary": "Penasihat Khusus Presiden RI Bidang Ketenagakerjaan dan Kesejahteraan Buruh&nbsp;Said Iqbal&nbsp;menemui Menteri ...",
      "published": "2026-07-09T10:35:07+00:00",
      "source": "Antara News",
      "groups": [
        "Government / Policy"
      ],
      "matched": [
        "menteri"
      ],
      "big": false,
      "id": "eda240dd36811759"
    },
    {
      "title": "Kemlu: Delegasi RI ke Iran hormati Khamenei dan perkuat bilateral",
      "link": "https://www.antaranews.com/berita/5642487/kemlu-delegasi-ri-ke-iran-hormati-khamenei-dan-perkuat-bilateral",
      "summary": "Kunjungan Menteri Luar Negeri (Menlu) RI Sugiono dan Ketua MPR RI Ahmad Muzani ke Iran&nbsp;untuk memberi penghormatan ...",
      "published": "2026-07-09T10:28:21+00:00",
      "source": "Antara News",
      "groups": [
        "Government / Policy"
      ],
      "matched": [
        "MPR",
        "menteri"
      ],
      "big": false,
      "id": "5ec970b6b570ba6c"
    },
    {
      "title": "Prabowo: RI jadi negara pertama yang menerapkan mandatori B50",
      "link": "https://www.antaranews.com/berita/5642480/prabowo-ri-jadi-negara-pertama-yang-menerapkan-mandatori-b50",
      "summary": "Presiden Prabowo Subianto menyatakan Indonesia resmi menjadi negara pertama di dunia yang menerapkan kebijakan ...",
      "published": "2026-07-09T10:25:42+00:00",
      "source": "Antara News",
      "groups": [
        "Government / Policy"
      ],
      "matched": [
        "Prabowo"
      ],
      "big": false,
      "id": "57c94249d8c00655"
    },
    {
      "title": "Prabowo tegaskan dorong kemandirian energi sejak sebelum jadi Presiden",
      "link": "https://www.antaranews.com/berita/5642479/prabowo-tegaskan-dorong-kemandirian-energi-sejak-sebelum-jadi-presiden",
      "summary": "Presiden Prabowo Subianto menegaskan upaya mewujudkan kemandirian energi telah menjadi arah kebijakannya sejak sebelum ...",
      "published": "2026-07-09T10:24:46+00:00",
      "source": "Antara News",
      "groups": [
        "Government / Policy"
      ],
      "matched": [
        "Prabowo"
      ],
      "big": false,
      "id": "892cca51ce2d5022"
    },
    {
      "title": "Prabowo: Ladang gas besar di Andaman-Masela dukung kemandirian energi",
      "link": "https://www.antaranews.com/berita/5642469/prabowo-ladang-gas-besar-di-andaman-masela-dukung-kemandirian-energi",
      "summary": "Presiden Prabowo Subianto mengungkapkan Indonesia menemukan ladang gas besar baru di perairan Andaman, Aceh&nbsp;serta ...",
      "published": "2026-07-09T10:19:02+00:00",
      "source": "Antara News",
      "groups": [
        "Government / Policy"
      ],
      "matched": [
        "Prabowo"
      ],
      "big": false,
      "id": "5d72f5de4f1334eb"
    },
    {
      "title": "Indonesia komitmen perkuat sistem internasional yang lebih efektif",
      "link": "https://www.antaranews.com/berita/5642464/indonesia-komitmen-perkuat-sistem-internasional-yang-lebih-efektif",
      "summary": "Menteri Luar Negeri RI Sugiono menyatakan bahwa Indonesia berkomitmen untuk berperan aktif dalam kerja sama ...",
      "published": "2026-07-09T10:11:47+00:00",
      "source": "Antara News",
      "groups": [
        "Government / Policy"
      ],
      "matched": [
        "menteri"
      ],
      "big": false,
      "id": "6893d6f157457427"
    },
    {
      "title": "IHSG ditutup menguat seiring maraknya aksi IPO di pasar modal",
      "link": "https://www.antaranews.com/berita/5642459/ihsg-ditutup-menguat-seiring-maraknya-aksi-ipo-di-pasar-modal",
      "summary": "IHSG Indeks Harga Saham Gabungan (IHSG) Bursa Efek Indonesia (BEI) pada Kamis sore ditutup menguat seiring maraknya ...",
      "published": "2026-07-09T10:09:16+00:00",
      "source": "Antara News",
      "groups": [
        "Global Finance",
        "Macro / Economy"
      ],
      "matched": [
        "IHSG",
        "IPO",
        "bursa efek Indonesia"
      ],
      "big": false,
      "id": "1e6ce7bfa67e2839"
    },
    {
      "title": "Bappenas: Cadangan beras pemerintah lampaui target per semester I",
      "link": "https://www.antaranews.com/berita/5642447/bappenas-cadangan-beras-pemerintah-lampaui-target-per-semester-i",
      "summary": "Kementerian Perencanaan Pembangunan Nasional/Badan Perencanaan Pembangunan Nasional (PPN/Bappenas) melaporkan ...",
      "published": "2026-07-09T10:04:36+00:00",
      "source": "Antara News",
      "groups": [
        "Government / Policy"
      ],
      "matched": [
        "Bappenas"
      ],
      "big": false,
      "id": "db0728ea3504dd4c"
    },
    {
      "title": "Prabowo minta Erick Thohir cari cara agar Indonesia masuk Piala Dunia",
      "link": "https://www.antaranews.com/berita/5642443/prabowo-minta-erick-thohir-cari-cara-agar-indonesia-masuk-piala-dunia",
      "summary": "Presiden Prabowo Subianto meminta Menteri Pemuda dan Olahraga yang juga Ketua Umum Persatuan Sepak Bola Seluruh ...",
      "published": "2026-07-09T10:03:01+00:00",
      "source": "Antara News",
      "groups": [
        "Government / Policy"
      ],
      "matched": [
        "Prabowo",
        "menteri"
      ],
      "big": false,
      "id": "25756de8d92131e9"
    },
    {
      "title": "Pimpinan KPK temui Menkeu Purbaya guna bahas usulan tambahan anggaran",
      "link": "https://www.antaranews.com/berita/5642429/pimpinan-kpk-temui-menkeu-purbaya-guna-bahas-usulan-tambahan-anggaran",
      "summary": "Pimpinan Komisi Pemberantasan Korupsi (KPK) menemui Menteri Keuangan (Menkeu) Purbaya Yudhi Sadewa di Kantor ...",
      "published": "2026-07-09T09:58:44+00:00",
      "source": "Antara News",
      "groups": [
        "Government / Policy"
      ],
      "matched": [
        "KPK",
        "anggaran",
        "menteri"
      ],
      "big": false,
      "id": "e8a4d62d53cea0cc"
    },
    {
      "title": "Bappenas catat pengadaan jagung capai 190 ribu ton per Juli",
      "link": "https://www.antaranews.com/berita/5642425/bappenas-catat-pengadaan-jagung-capai-190-ribu-ton-per-juli",
      "summary": "Kementerian Perencanaan Pembangunan Nasional/Badan Perencanaan Pembangunan Nasional (PPN/Bappenas) mencatat pengelolaan ...",
      "published": "2026-07-09T09:57:09+00:00",
      "source": "Antara News",
      "groups": [
        "Government / Policy"
      ],
      "matched": [
        "Bappenas"
      ],
      "big": false,
      "id": "bf3c8dda226846b3"
    },
    {
      "title": "Produk UMKM bisa kuasai pasar ritel modern jika terapkan kolaborasi",
      "link": "https://www.antaranews.com/berita/5642420/produk-umkm-bisa-kuasai-pasar-ritel-modern-jika-terapkan-kolaborasi",
      "summary": "&nbsp;\n\nMenteri Perdagangan RI Budi Santoso&nbsp;mengatakan, produk usaha mikro, kecil, dan menengah (UMKM) bisa ...",
      "published": "2026-07-09T09:56:13+00:00",
      "source": "Antara News",
      "groups": [
        "Government / Policy"
      ],
      "matched": [
        "menteri"
      ],
      "big": false,
      "id": "41cbf28abd09acd0"
    },
    {
      "title": "KSP apresiasi MPP Gianyar Bali pangkas birokrasi layanan masyarakat",
      "link": "https://www.antaranews.com/berita/5642416/ksp-apresiasi-mpp-gianyar-bali-pangkas-birokrasi-layanan-masyarakat",
      "summary": "Kantor Staf Presiden (KSP)&nbsp;menilai Mal Pelayanan Publik (MPP) Gianyar, Bali, dapat memangkas birokrasi karena ...",
      "published": "2026-07-09T09:55:20+00:00",
      "source": "Antara News",
      "groups": [
        "Macro / Economy"
      ],
      "matched": [
        "apresiasi"
      ],
      "big": false,
      "id": "6f8ea413361eb426"
    },
    {
      "title": "Pakar sebut penugasan Muzani ke pemakaman Khamenei konstitusional",
      "link": "https://www.antaranews.com/berita/5642415/pakar-sebut-penugasan-muzani-ke-pemakaman-khamenei-konstitusional",
      "summary": "Pakar hukum tata negara Universitas Muslim Indonesia Fahri Bachmid menilai penugasan Ketua MPR RI Ahmad Muzani ...",
      "published": "2026-07-09T09:53:22+00:00",
      "source": "Antara News",
      "groups": [
        "Government / Policy"
      ],
      "matched": [
        "MPR"
      ],
      "big": false,
      "id": "ec7b797a5f107bc9"
    },
    {
      "title": "Trump sebut Spanyol \"akhirnya kembali\" setelah diancam",
      "link": "https://www.antaranews.com/berita/5642395/trump-sebut-spanyol-akhirnya-kembali-setelah-diancam",
      "summary": "Presiden Amerika Serikat Donald Trump mengatakan Spanyol berbalik arah sepenuhnya&nbsp;setelah dia&nbsp;mengancam akan ...",
      "published": "2026-07-09T09:45:12+00:00",
      "source": "Antara News",
      "groups": [
        "Geopolitics"
      ],
      "matched": [
        "Trump"
      ],
      "big": false,
      "id": "376cd6b24bb96512"
    },
    {
      "title": "Why are politicians and sanctioned states embracing crypto?",
      "link": "https://www.aljazeera.com/video/counting-the-cost/2026/7/9/why-is-the-cryptocurrency-market-slumping?traffic_source=rss",
      "summary": "Bitcoin is falling, yet cryptocurrency is spreading beyond investing into politics, sanctions and global finance.",
      "published": "2026-07-09T08:48:32+00:00",
      "source": "Al Jazeera",
      "groups": [
        "Global Finance"
      ],
      "matched": [
        "Bitcoin",
        "crypto",
        "sanctions"
      ],
      "big": false,
      "id": "96d41cd5f7f1e89c"
    },
    {
      "title": "Trump says he will remove Syria from the state sponsor of terrorism list",
      "link": "https://www.aljazeera.com/video/newsfeed/2026/7/9/trump-says-he-will-remove-syria-from-the-state-sponsor-of-terrorism-list?traffic_source=rss",
      "summary": "US President Trump said he will remove Syria from the US state sponsor of terrorism list at the NATO summit.",
      "published": "2026-07-09T04:28:44+00:00",
      "source": "Al Jazeera",
      "groups": [
        "Geopolitics"
      ],
      "matched": [
        "Trump"
      ],
      "big": false,
      "id": "3d9e4a325826fb11"
    },
    {
      "title": "US court rules that Trump’s name must stay off Kennedy Center during appeal",
      "link": "https://www.aljazeera.com/news/2026/7/9/us-court-rules-that-trumps-name-must-stay-off-kennedy-center-during-appeal?traffic_source=rss",
      "summary": "Trump’s name was removed from the centre&#039;s facade and signage last month, after a judge ordered its removal.",
      "published": "2026-07-09T03:57:46+00:00",
      "source": "Al Jazeera",
      "groups": [
        "Geopolitics"
      ],
      "matched": [
        "Trump"
      ],
      "big": false,
      "id": "6ce73357f0e88cea"
    },
    {
      "title": "Pertamina berikan sanksi SPBU di Timika tak boleh jual Pertalite",
      "link": "https://www.antaranews.com/berita/5641812/pertamina-berikan-sanksi-spbu-di-timika-tak-boleh-jual-pertalite",
      "summary": "PT Pertamina Patra Niaga memberikan sanksi sementara kepada Stasiun Pengisian Bahan Bakar Umum (SPBU) di Jalan ...",
      "published": "2026-07-09T03:47:59+00:00",
      "source": "Antara News",
      "groups": [
        "Commodity / Energy Policy"
      ],
      "matched": [
        "Pertamina"
      ],
      "big": false,
      "id": "0e12774cf02f92e5"
    },
    {
      "title": "Menko PM pastikan pelayanan BPJS tanpa diskriminasi",
      "link": "https://www.antaranews.com/berita/5641808/menko-pm-pastikan-pelayanan-bpjs-tanpa-diskriminasi",
      "summary": "Menteri Koordinator Bidang Pemberdayaan Masyarakat (Menko PM), Abdul Muhaimin Iskandar memastikan pelayanan BPJS ...",
      "published": "2026-07-09T03:47:50+00:00",
      "source": "Antara News",
      "groups": [
        "Government / Policy"
      ],
      "matched": [
        "menteri"
      ],
      "big": false,
      "id": "70cb35f9a65bde08"
    },
    {
      "title": "Wamenkomdigi ungkap dua aspek krusial wujudkan AI nasional berdaulat",
      "link": "https://www.antaranews.com/berita/5641807/wamenkomdigi-ungkap-dua-aspek-krusial-wujudkan-ai-nasional-berdaulat",
      "summary": "Wakil Menteri Komunikasi dan Digital (Wamenkomdigi) Nezar Patria mengungkapkan dua aspek yang krusial untuk ...",
      "published": "2026-07-09T03:46:12+00:00",
      "source": "Antara News",
      "groups": [
        "Government / Policy"
      ],
      "matched": [
        "menteri"
      ],
      "big": false,
      "id": "2cac106bd5c3a0db"
    },
    {
      "title": "Menteri UMKM: Lebih dari 90 persen UMKM belum manfaatkan AI",
      "link": "https://www.antaranews.com/berita/5641803/menteri-umkm-lebih-dari-90-persen-umkm-belum-manfaatkan-ai",
      "summary": "Menteri Usaha Mikro, Kecil, dan Menengah (UMKM) Maman Abdurrahman mengatakan lebih dari 90 persen pelaku UMKM di ...",
      "published": "2026-07-09T03:45:05+00:00",
      "source": "Antara News",
      "groups": [
        "Government / Policy"
      ],
      "matched": [
        "menteri"
      ],
      "big": false,
      "id": "2da38ef0fcc19a24"
    },
    {
      "title": "Wamen ATR: Kepala daerah miliki peran untuk selesaikan konflik agraria",
      "link": "https://www.antaranews.com/berita/5641799/wamen-atr-kepala-daerah-miliki-peran-untuk-selesaikan-konflik-agraria",
      "summary": "Wakil Menteri Agraria dan Tata Ruang/Wakil Kepala Badan Pertanahan Nasional (Wamen ATR/Waka BPN) Ossy Dermawan ...",
      "published": "2026-07-09T03:41:15+00:00",
      "source": "Antara News",
      "groups": [
        "Government / Policy"
      ],
      "matched": [
        "menteri"
      ],
      "big": false,
      "id": "65318868bb74d163"
    },
    {
      "title": "Komisi III DPR dukung Polri usut dugaan korupsi batubara",
      "link": "https://www.antaranews.com/berita/5641791/komisi-iii-dpr-dukung-polri-usut-dugaan-korupsi-batubara",
      "summary": "Ketua Komisi III DPR RI Habiburokhman mendukung Korps Pemberantasan Tindak Pidana Korupsi (Kortastipidkor) Polri untuk ...",
      "published": "2026-07-09T03:36:35+00:00",
      "source": "Antara News",
      "groups": [
        "Commodity / Energy Policy",
        "Government / Policy"
      ],
      "matched": [
        "DPR",
        "batubara"
      ],
      "big": false,
      "id": "7135ae11264ad55a"
    },
    {
      "title": "Kemdiktisaintek gandeng sejumlah PTN bangun ekosistem Sekolah Garuda",
      "link": "https://www.antaranews.com/berita/5641789/kemdiktisaintek-gandeng-sejumlah-ptn-bangun-ekosistem-sekolah-garuda",
      "summary": "Menteri Pendidikan Tinggi, Sains, dan Teknologi (Mendiktisaintek),&nbsp;Brian Yuliarto mendorong terbangunnya ...",
      "published": "2026-07-09T03:27:02+00:00",
      "source": "Antara News",
      "groups": [
        "Government / Policy"
      ],
      "matched": [
        "menteri"
      ],
      "big": false,
      "id": "66404a7e3c5225e5"
    },
    {
      "title": "What’s with Trump’s sudden fixation on communism?",
      "link": "https://www.aljazeera.com/video/newsfeed/2026/7/9/whats-with-trumps-sudden-fixation-on-communism?traffic_source=rss",
      "summary": "US President Donald Trump has denounced communism more than 80 times in the past two weeks.",
      "published": "2026-07-09T03:22:27+00:00",
      "source": "Al Jazeera",
      "groups": [
        "Geopolitics"
      ],
      "matched": [
        "Trump"
      ],
      "big": false,
      "id": "ba302b9584eb8cb5"
    },
    {
      "title": "Watch President Trump Prepares for NATO Summit | Daybreak Europe 7/6/2026 - Bloomberg.com",
      "link": "https://news.google.com/rss/articles/CBMihgFBVV95cUxPcDJnMjJfNGJ2NkZVTU5GbEI3MkRGVVg5dl9pWHJIZmt4d2JHYTdDeU5OV0x5alVLcFdidVpUMVBpMWVqRFhsd3JfUU1MQkpNUFRQbTgwaC13VVlHRldxaUtxbjU2TkZacUw5WXZkcDN6cm9WdjhCcmFNaFNiemR4aWt5WTN3QQ?oc=5",
      "summary": "Watch President Trump Prepares for NATO Summit | Daybreak Europe 7/6/2026&nbsp;&nbsp;Bloomberg.com",
      "published": "2026-07-06T00:00:00+00:00",
      "source": "Bloomberg (via GNews)",
      "groups": [
        "Geopolitics"
      ],
      "matched": [
        "Trump"
      ],
      "big": false,
      "id": "2776b8d487abf79e"
    },
    {
      "title": "Watch Trump Seeks to Put Himself Center Stage for US Independence Day - Bloomberg.com",
      "link": "https://news.google.com/rss/articles/CBMirwFBVV95cUxQMmVlMlI0d0tFTkxWa2NiR1Ftdks2Q1lNRk9RT3FjLWJ1N1VBaDI4dkZiS2RieTY0UHlFUEJrRHliZnNrdS1FdlRPT3ZyTGtOa1lid2p5NTI5TlI2d3pEUlZKSUV4VG9fWm80X2ctNjlHSUZOcGJMUlZLNEF1ZmprVUx5czJ1dzlDNUlrMTkzUEZkUVBiUnk5ckhzaks2MVlnUzU2SVZlWU1zZ095VHhz?oc=5",
      "summary": "Watch Trump Seeks to Put Himself Center Stage for US Independence Day&nbsp;&nbsp;Bloomberg.com",
      "published": "2026-07-04T00:00:00+00:00",
      "source": "Bloomberg (via GNews)",
      "groups": [
        "Geopolitics"
      ],
      "matched": [
        "Trump"
      ],
      "big": false,
      "id": "c112061c92c6b84f"
    },
    {
      "title": "BI Naikkan Suku Bunga ke 5,50%, Rupiah dan Inflasi Jadi Pertimbangan Utama - MUC Consulting",
      "link": "https://news.google.com/rss/articles/CBMiogFBVV95cUxNRHBKUTlfTzNCdXRhVVVaWmN5c1lKZ2dYd0NjdTBsWWR6cDdJdzJzUThEQkwwVWdQTHEwWHJKR3hiNk1mWVpza0ZsdmoyY01CSGJOQV9ubmJJcnhMWHl1TV9rb0dETTcwY0xBYXhmLXd2cGs3dE5veWp4cjFIdkNmSnZlX2FqSVN1RFpXQWJoSm9aZmlnRjZ5VlFBRlludTl2RVE?oc=5",
      "summary": "BI Naikkan Suku Bunga ke 5,50%, Rupiah dan Inflasi Jadi Pertimbangan Utama&nbsp;&nbsp;MUC Consulting",
      "published": "2026-06-25T07:00:00+00:00",
      "source": "GNews – BI rate rupiah",
      "groups": [
        "Macro / Economy"
      ],
      "matched": [
        "inflasi",
        "rupiah",
        "suku bunga"
      ],
      "big": true,
      "id": "7910b44657b9c6d0"
    },
    {
      "title": "Setelah BI Rate 5,75%, Seberapa Kuat Rupiah Bertahan hingga Akhir Tahun? - kontan.co.id",
      "link": "https://news.google.com/rss/articles/CBMipwFBVV95cUxPZGtzT09QYm1OVm9PTVh6emNmZUJfdWpoT2dZc2g1QkdNYmtEa2pWbkdTVWZfcF9JQkpWZTlqc1lydlhKS0pOT2ZjT0lUZlFsZFZGaHBINHpnVkNHc0J3SUk3R05Mamp1QnVUN0V1b24zSVctNnRLakZsdWg3MWg3aVRibi1INTlCSmZDd1ZiQlE2OEZWYzIxUGdDeVBGb2V6MVhwVjJwSdIBnwFBVV95cUxOeFlGLXBkNlFjMzZKT2tvLWdtRHN1Rm5temFFUkc2cngxRTlMMkRyekxncmRPMDlFZmFIUmRYbUJWSHBBTzF2d3lzaWJLQkVXLUVFc0lHanFNZ044Q0cybmdWNE1idGZ6RUZ5RDNMUmJYbHd5RFFVcmpCRkRJOE1iTG13cjRlZWxCd2tNRnB5MkVGS3ZDWl9EMWNFRDlhSTA?oc=5",
      "summary": "Setelah BI Rate 5,75%, Seberapa Kuat Rupiah Bertahan hingga Akhir Tahun?&nbsp;&nbsp;kontan.co.id",
      "published": "2026-06-19T07:00:00+00:00",
      "source": "GNews – BI rate rupiah",
      "groups": [
        "Macro / Economy"
      ],
      "matched": [
        "BI rate",
        "rupiah"
      ],
      "big": true,
      "id": "722355ee78f35d48"
    },
    {
      "title": "Coal prices soar on Indonesia export controls, China mine disaster - Nikkei Asia",
      "link": "https://news.google.com/rss/articles/CBMiqAFBVV95cUxQOHlDX3h6VDRVSXhvdnlaQ3lnZmU1QTBCSlBUVklrbGloNzRaZkROMGhpQlpKVjQwc2UwLW85cWxBcUZPNjhXcXJyLU1KNDlBdHp5Wl9kMU0yYXZyUlJxb1owVmUxYWhvVVpsdWtaYko3RnBuQnFDMkpDR1F0NFBUYU5KeW1IaEFXREhwb005U2JXcEFTTTFlU0NKakFkUTNuRVY1QWRHMXI?oc=5",
      "summary": "Coal prices soar on Indonesia export controls, China mine disaster&nbsp;&nbsp;Nikkei Asia",
      "published": "2026-06-18T07:00:00+00:00",
      "source": "Nikkei Asia (via GNews)",
      "groups": [
        "Global Finance"
      ],
      "matched": [
        "coal price"
      ],
      "big": false,
      "id": "51c4aef6b4f019be"
    },
    {
      "title": "BI Dinilai Belum Perlu Naikkan Bunga di RDG Juni, Rupiah dan Inflasi Sudah Membaik - kontan.co.id",
      "link": "https://news.google.com/rss/articles/CBMitwFBVV95cUxPTGRIWDVGMWEwZXI2eHd5bzFfelk0UXVSRlc2MTRHSExNcjFqYXhOUmRRWTNSNGFMQm1yNVFYS2NTbXlINER4djY0S3Zhc3JmaFg5Zi04OFJXdlA3a1RZTTA1WW1iVXRuTV9jXzMyb09yYmtUek5ueGduOWdYZXJRX3VJV2RfUXdIajljOU1JNkFBakhuTmw4RmNjcGY4YWwzbUlsQkduV1ZwbHF5bDBpbWxGSHc0MTjSAbABQVVfeXFMUDduMDU4ZWgzUWM2ZTN0NzZCVDNOb1owcS1YOGlIVzFMTjhKRng3eGdPMTFHdkNOMUVWSVhEcDZ2QW00QzN0cEkteXQ0VG5FcWtZMWFBVGpXcWtybzVzSTV3N051MEdBQldwbHVYZG9EVHVxM042T05VV2xCeHdvam1XLUg1SEhvcHBTX1RucUJTX19QLW1RNVp4dXNlX3hmT1Z1clZjUnVPSTEyWjI2dU0?oc=5",
      "summary": "BI Dinilai Belum Perlu Naikkan Bunga di RDG Juni, Rupiah dan Inflasi Sudah Membaik&nbsp;&nbsp;kontan.co.id",
      "published": "2026-06-16T07:00:00+00:00",
      "source": "GNews – BI rate rupiah",
      "groups": [
        "Macro / Economy"
      ],
      "matched": [
        "inflasi",
        "rupiah"
      ],
      "big": true,
      "id": "d00f5f4b9b169673"
    },
    {
      "title": "Klaim Hemat APBN Rp300 Triliun, Kepala Bakom Minta Mahasiswa Dukung Prabowo Lawan Kebocoran Anggaran - Warta Ekonomi",
      "link": "https://news.google.com/rss/articles/CBMi0wFBVV95cUxPRmp4cXU3YW9SQmtXQ29UNjNJbTB6ZUZ2OGlCWmR4aWlTZm00RXl2NGdtRjFrM0NIVEUzUDNWVHN6ZS1SYTBwb0l1VndWenlIV2R4UkNhbmlVb1NMNmlCd3lhaVZHVUJsNG8zY215NGlUMW43enEtR2VrSTcwOW04SXdkaUxZVEpWZEVLQWh6ZFFJWTNLRzZDSjZpeGlibU1qRjJBbDk0WnhrOTg3M1ZlbWQ0TWpTOC1HSk40ZFhVZnFISjZJVkc4d01MdEphamlhVG9B?oc=5",
      "summary": "Klaim Hemat APBN Rp300 Triliun, Kepala Bakom Minta Mahasiswa Dukung Prabowo Lawan Kebocoran Anggaran&nbsp;&nbsp;Warta Ekonomi",
      "published": "2026-06-15T07:00:00+00:00",
      "source": "GNews – Prabowo APBN",
      "groups": [
        "Government / Policy"
      ],
      "matched": [
        "APBN",
        "Prabowo",
        "anggaran"
      ],
      "big": true,
      "id": "f8d18b6e5f52d2d8"
    },
    {
      "title": "Wholesale prices rose 1.1% in May, more than expected, on surge in energy",
      "link": "https://www.cnbc.com/2026/06/11/producer-price-index-may-2026-.html",
      "summary": "The producer price index was expected to increase 0.7% in May, according to the Dow Jones consensus forecast.",
      "published": "2026-06-11T16:25:00+00:00",
      "source": "CNBC Global Markets",
      "groups": [
        "Global Finance"
      ],
      "matched": [
        "Dow Jones"
      ],
      "big": false,
      "id": "205f407cdebf9677"
    },
    {
      "title": "World Bank says Indonesia's GDP to slow to 5% in 2026 as fiscal pressures rise - Reuters",
      "link": "https://news.google.com/rss/articles/CBMiuwFBVV95cUxPZkdIMmFsLTE1TXNyZVc5MmtqYnROdFY5dHlQUXRhY0twbjhyNEgyZTlGd1M5VGRfanZVOTN6aE1ETkxYYWJrU3A2ekVvc3JLZ0pESlZ6T204N1Q5UUllcU05cHVpTUpxT1FhNG5kUjZUM3dRcmxjdThnWkhwZmVNNFhvVWJqZ05FaTVuRWozZTRUb2pXcm1wX3RfYlQ2MjZBOG85Y0RndVgzRlFQVFo4bXZXNmFzT2cyQVVZ?oc=5",
      "summary": "World Bank says Indonesia's GDP to slow to 5% in 2026 as fiscal pressures rise&nbsp;&nbsp;Reuters",
      "published": "2026-06-11T07:00:00+00:00",
      "source": "Reuters – Indonesia",
      "groups": [
        "Global Finance"
      ],
      "matched": [
        "World Bank"
      ],
      "big": false,
      "id": "5a892c87d58e22ef"
    },
    {
      "title": "Wapres Gibran Dampingi Presiden Prabowo Sampaikan Arah Kebijakan Ekonomi 2027 dalam Rapat Paripurna DPR RI - Target Berita",
      "link": "https://news.google.com/rss/articles/CBMizwFBVV95cUxNTjIxNElGb2FYMnN0M3pYRHJvN3lBTC1POWo5cjlYY1Y4Z0M1cFZqVnY3MEZmaF9JWXJQZmxCZ0c4X3E3RGZOYTBvUGQxOFdCMHczWnNpVjF1bHAycmZteFhNQmVyenhaVE5SS25ZOC1FcVEwQ1dvVWswQWJONUQ4MXlmVlFDd0xLalhySkZENjhWbm5NbEtRbHJSNTAwSi1sUno5NVdJVHBGRHVwTklFVkE2SHVEdGlDQ19IMlcwb2RaY1gyR19SS29PX20zeHM?oc=5",
      "summary": "Wapres Gibran Dampingi Presiden Prabowo Sampaikan Arah Kebijakan Ekonomi 2027 dalam Rapat Paripurna DPR RI&nbsp;&nbsp;Target Berita",
      "published": "2026-05-24T07:00:00+00:00",
      "source": "GNews – Prabowo APBN",
      "groups": [
        "Government / Policy"
      ],
      "matched": [
        "DPR",
        "Gibran",
        "Prabowo"
      ],
      "big": false,
      "id": "ba85d0e79469d198"
    },
    {
      "title": "Membaca Ulang Pidato Lengkap Prabowo di DPR, Ini Poinnya - Infobanknews",
      "link": "https://news.google.com/rss/articles/CBMikwFBVV95cUxQdW5IZXFGSmxfQ3VHbXVSNnVlZGlWekJVRXVTM05SQjhNUm5qb25GY1NFWll5TzRCOWdmSTAzdW1EeXdiX0EyNEc3UVBYWTE0bVBDWFR5eUJWRkVqZFk1OFhaV2tVdG5JbW5xNEV0YVlEdDlnZ3UtZDZPcFBObGVHQ0xQY3pzdTNYdG5XMUxacGRRTzg?oc=5",
      "summary": "Membaca Ulang Pidato Lengkap Prabowo di DPR, Ini Poinnya&nbsp;&nbsp;Infobanknews",
      "published": "2026-05-21T07:00:00+00:00",
      "source": "GNews – Prabowo APBN",
      "groups": [
        "Government / Policy"
      ],
      "matched": [
        "DPR",
        "Prabowo"
      ],
      "big": false,
      "id": "44d5f9b5f3198777"
    },
    {
      "title": "BI Rate Naik Tinggi, Bank Indonesia Yakin Nilai Tukar Rupiah Membaik - KONTAN",
      "link": "https://news.google.com/rss/articles/CBMiowFBVV95cUxPSlhWR1J5QzZnQ0x2VHRRa3BkTUFDY2VWbEljRnEyOEFlSmllWjR4WUI5QlhFdDVqTTRnOWtsbmRDUDNfOFdCOHA1VUVURWZYakJ0bTVaTm5wdG8xS2FQZ3ZSM2l0Mi1QZXYwMW4xaGx0bEFRUlFUT2xhR1JsaHc5c29wQmdFR3JQRnNFbm42M0NEM090Smc2Z1BZbWJrQnNjY29z?oc=5",
      "summary": "BI Rate Naik Tinggi, Bank Indonesia Yakin Nilai Tukar Rupiah Membaik&nbsp;&nbsp;KONTAN",
      "published": "2026-05-20T07:00:00+00:00",
      "source": "GNews – BI rate rupiah",
      "groups": [
        "Macro / Economy"
      ],
      "matched": [
        "BI rate",
        "Bank Indonesia",
        "rupiah"
      ],
      "big": true,
      "id": "b763e0916b0aa5b6"
    },
    {
      "title": "Presiden Prabowo Sampaikan Arah Kebijakan Fiskal Tahun 2027, Tekankan APBN sebagai Alat Perjuangan Bangsa - Kementerian Keuangan",
      "link": "https://news.google.com/rss/articles/CBMinAFBVV95cUxNVUZJb01pRWJKMGV1ZXMyUE92WFNwVlhucTRvTDEtUzdaWldLTXQxZVBHdWJzbUtWd0V5VGtiTERvRm5NTUxUVDVNdG5QSzk1NTdRY2g5ei1lWndnS3FCY2VyVldNX0FGa1NZWm1ubVozVE9WZ0pBc0dEUnBIS0hEdDB2RHBpc0hUeGNjNjh3NWJzZktDeUl0eUJtNWU?oc=5",
      "summary": "Presiden Prabowo Sampaikan Arah Kebijakan Fiskal Tahun 2027, Tekankan APBN sebagai Alat Perjuangan Bangsa&nbsp;&nbsp;Kementerian Keuangan",
      "published": "2026-05-20T07:00:00+00:00",
      "source": "GNews – Prabowo APBN",
      "groups": [
        "Government / Policy"
      ],
      "matched": [
        "APBN",
        "Prabowo"
      ],
      "big": true,
      "id": "d372102daaa92e7b"
    },
    {
      "title": "Prabowo Targetkan Ekonomi Tumbuh 6,5 Persen pada 2027, Defisit APBN Dijaga Maksimal 2,4 Persen - TopBusiness.id",
      "link": "https://news.google.com/rss/articles/CBMiygFBVV95cUxNYTd3NUk0Z3E3ZER2ZUFJWjZSRW5YXzBnMVRCVnZhU2NxNnpCa0hUaUNhZ3lGcGJoMmdFaVFxZ3RYS0FxdXhtVzJHVmYwTXN5Um83VURhRXc0M0ppQXVUN1FzRHFOVy1tZHNsRS13SnhGYlhJNk5jb2NiNmRiajAtOHZTcEZ4ZHQ2NnM1M2s2c21BNzlObnpRd0t3cnZBdUNBVlRRMkFlSTMteDMtX240MWdIUUt0SFMwRnZwVnRDUXhjdy1kWWpqX01B?oc=5",
      "summary": "Prabowo Targetkan Ekonomi Tumbuh 6,5 Persen pada 2027, Defisit APBN Dijaga Maksimal 2,4 Persen&nbsp;&nbsp;TopBusiness.id",
      "published": "2026-05-20T07:00:00+00:00",
      "source": "GNews – Prabowo APBN",
      "groups": [
        "Government / Policy"
      ],
      "matched": [
        "APBN",
        "Prabowo"
      ],
      "big": true,
      "id": "655bd6f27a651dd0"
    },
    {
      "title": "Prabowo Besok Pidato Kerangka Ekonomi Makro, Purbaya: Ini Sejarah! - detikFinance",
      "link": "https://news.google.com/rss/articles/CBMivgFBVV95cUxQR3lfVHg3VUc4NE9LdzRZdnM2Z2dJTWpJQWhKNlFjd1BSOWJPTTRvWTVXaC1zUzFQcHF6WEpneXE5NjdNdHcyRlpRX0xJT2VERDB3SnBFcG0yUWpxaVpRX1NaX2dBaHlJekVJMmQ3N0UwenZIc2lWcDlZblhHUVhZdEVwaFBJN2RBTlVwajZnZGpLTUlMM1JhRXZBSXZQNnB3a0NRaTVHQ3R3SVJtWjRSMGs3MDlNR1ltVkFVai1B0gHDAUFVX3lxTE9aanRZVGp6ZlNiMnBsQzVMTkMtMGRQTmhncWxyWmRoRXZBZHhweUw2WjlucmVRWlY1Mmxfb21iT1hWeW5TXzlLQXRSMUZUTVd3U1drX1liYjN6NS1pSktLYThFTFZvVjlTS1Bmd05hMTBjZmdVUzZra1h1d3RrNUljT3FoRWc0cmVObTVZN2lDRmhrVllVMVlSUGgtQ3FkanRnbGxlcXNnYV9mNXZFUVRWY2I5bkozcTVPZkJib25CMEZZbw?oc=5",
      "summary": "Prabowo Besok Pidato Kerangka Ekonomi Makro, Purbaya: Ini Sejarah!&nbsp;&nbsp;detikFinance",
      "published": "2026-05-19T07:00:00+00:00",
      "source": "GNews – Prabowo APBN",
      "groups": [
        "Government / Policy"
      ],
      "matched": [
        "Prabowo"
      ],
      "big": false,
      "id": "8b631e46ae7518bd"
    },
    {
      "title": "Amukan Trump Datang Bertubi-tubi, Apa yang Akan Dipilih BI Besok? - CNBC Indonesia",
      "link": "https://news.google.com/rss/articles/CBMixwFBVV95cUxNOEhLTUt3czlBUmR6MU54MWk2ZGwtUW5FX2pfcXlDQ3QzMTZoWkVQNnBQMWE2bEdqT2c0MXlBRzZoNnhGYnpfOG94TUYzbE1jS3hXQ1NlcGNmMFFVckkxcGF5aEFETTBwak1nY2Nlbl9uMkJyV2k0TFJBdWFmREc0TFQtekFPbm9iSTlxOWlwSDZKNFhGT0lPR1hTaUtuNXM1N1NOVlo4VkZVY2p4YTBtb050YUxVWk5kZnJ4ekJBZUpQcDFyc2lv?oc=5",
      "summary": "Amukan Trump Datang Bertubi-tubi, Apa yang Akan Dipilih BI Besok?&nbsp;&nbsp;CNBC Indonesia",
      "published": "2026-04-21T07:00:00+00:00",
      "source": "GNews – BI rate rupiah",
      "groups": [
        "Geopolitics"
      ],
      "matched": [
        "Trump"
      ],
      "big": false,
      "id": "b5606fe18764d19a"
    },
    {
      "title": "Strategi Fiskal Presiden Prabowo: Utang Dijaga di Bawah 40%, Defisit Tetap 3% - MetroTVNews.com",
      "link": "https://news.google.com/rss/articles/CBMitgFBVV95cUxQZDZORW5pT1ZwektRT1R0M2U0Qi1ZbmZhTVo4UElBc0s2ZUVMcExmX1h1cVBEWTB1c0ZyMGhMdlpGNXM2WGQtdW80MkFXcEMyT1QwaUdaSXprdUIyamV3bDFyV3A5dU1nMnhfdHpVaGFFUmtucnE2M2dzeUlPdWllRmZNYmdydVRsMWNQbkU0MU81ZzRZVWFVMU5WZVdBblROSmVXSjZ6bXhMOU16OGtTbzgyMkU2Zw?oc=5",
      "summary": "Strategi Fiskal Presiden Prabowo: Utang Dijaga di Bawah 40%, Defisit Tetap 3%&nbsp;&nbsp;MetroTVNews.com",
      "published": "2026-04-08T07:00:00+00:00",
      "source": "GNews – Prabowo APBN",
      "groups": [
        "Government / Policy"
      ],
      "matched": [
        "Prabowo"
      ],
      "big": false,
      "id": "e88e527e921f56b9"
    },
    {
      "title": "Pemerintah Gerak Cepat Menjaga Stabilitas di Tengah Pelemahan Rupiah - beritanasionalupdate.com",
      "link": "https://news.google.com/rss/articles/CBMiuwFBVV95cUxQVmF4Y3J4czBwLU1zTnlPMm5HX3ZUNGtMSkZoUlJhSTlVVDRyZjVaY3pvZ1lOQjRwOFB3SXk0NXotOWJXb2FBRE0wYjJmbE90cEdYTm12dEtNdW9qNktpblhkajNocUs3UzkyUzhoZG1JOS1tZzFxSGFtTTZVazJVNzZtOUNqUjBzV2tmOVRIWFEtU084ZGk3RkVSd0FnSUhWeXNBT1dmNVpUNHd0QTUtczFqem4yemZqMm5R?oc=5",
      "summary": "Pemerintah Gerak Cepat Menjaga Stabilitas di Tengah Pelemahan Rupiah&nbsp;&nbsp;beritanasionalupdate.com",
      "published": "2026-04-04T07:00:00+00:00",
      "source": "GNews – BI rate rupiah",
      "groups": [
        "Macro / Economy"
      ],
      "matched": [
        "rupiah"
      ],
      "big": true,
      "id": "dc0ba580d1c2e658"
    },
    {
      "title": "Soal Opsi Defisit APBN Lewati 3%, Purbaya Manut Arahan Prabowo - Bloomberg Technoz",
      "link": "https://news.google.com/rss/articles/CBMisgFBVV95cUxNbElFQ1kzc2VRT1J3el9VWmVydm9DRXVHd1dEVGFrb1dLRFViNktOamQ3bl93RTlrWTgzY2hXbEt2RDhZVjk0MElPMXl0T0h4OTVrMERtZlE5b2ZIYmVIR0ZaNUxHM2xmdWdkWUc2Rk9XM0ZpNWhTSGljTzN4dVJnTWZrZTBSZDhEeWY5ZXRwYW8wMElXUHBKMjg3ZW56TXdPekhRNmdELWFidUZsNGJueDFR?oc=5",
      "summary": "Soal Opsi Defisit APBN Lewati 3%, Purbaya Manut Arahan Prabowo&nbsp;&nbsp;Bloomberg Technoz",
      "published": "2026-03-13T07:00:00+00:00",
      "source": "GNews – Prabowo APBN",
      "groups": [
        "Government / Policy"
      ],
      "matched": [
        "APBN",
        "Prabowo"
      ],
      "big": true,
      "id": "4d02f207960c7912"
    },
    {
      "title": "Judge Gives Trump Administration More Time to Distribute Tariff Refunds - WSJ",
      "link": "https://news.google.com/rss/articles/CBMisgFBVV95cUxPRGNuOEVNYkMwOVM3QnV2XzIwZkRXV3dKMndmVTFEQTBsWnNLSmt6QVQxMzZqWmdLOS1PUFUyaDh2THY3NHBHcGZWOVhXRUszVmFFaWRFdmRuTGhoTVIzcUowLUliQVI1bHRrMVpDVmJsN1BnZXNrc015VUw3TDQ3SUtMbWRwQ1hvNWdSMWlPdjk1SWgtMkd6Y28yNGRUYlVBV20xVFdUMVFfRGN2ZTJ6UFNn?oc=5",
      "summary": "Judge Gives Trump Administration More Time to Distribute Tariff Refunds&nbsp;&nbsp;WSJ",
      "published": "2026-03-06T08:00:00+00:00",
      "source": "WSJ (via GNews)",
      "groups": [
        "Geopolitics",
        "Global Finance"
      ],
      "matched": [
        "Trump",
        "tariff"
      ],
      "big": false,
      "id": "1f32a410b77e9354"
    },
    {
      "title": "Bank Indonesia holds rates steady, focus remains on 'undervalued' rupiah - Reuters",
      "link": "https://news.google.com/rss/articles/CBMivgFBVV95cUxQTFZ6R2NMeEwxLTl0aHdWNVVIZFFsQW1tTUtQTWVMTGJQQTVsZTFqMzZoNXNrby1CbVpPYUZvOHZXTE1uUGZwel9KVGFXbGxwaXBzNXFwRi1KTDZhYmYzeG5rb3dSM2NxVmdKY1pVT0pvMU5vU1FNUERvQ0ZyZEdQUmQ5YklpRHA0THdHNElCWmlOdGpDQmhYU3JRakZHeWl3N0FKSExWVXdrLXk5WDJaZmQyUEVIZ25ubnFjLUhB?oc=5",
      "summary": "Bank Indonesia holds rates steady, focus remains on 'undervalued' rupiah&nbsp;&nbsp;Reuters",
      "published": "2026-02-19T08:00:00+00:00",
      "source": "Reuters – Indonesia",
      "groups": [
        "Macro / Economy"
      ],
      "matched": [
        "Bank Indonesia",
        "rupiah"
      ],
      "big": true,
      "id": "1fc976e2b5621ece"
    },
    {
      "title": "European Luxury Stocks Slump on Trump’s Tariff Threat - WSJ",
      "link": "https://news.google.com/rss/articles/CBMingFBVV95cUxQbENmR1RmZTZVVUo1S1ZkcXphQV9jeHRXM2l0eE9EVUFhcTUtZjRCN1Vka3ZUUDN0Ym9WQlFidGNOcEJQQW9BeVViazZVLTlkQmRlWmdKY01fYVIyOHV3dUlmTDlmOVVlV29nRnkwRWRfTEFFVXhqOUlBSUN5SzB3RGgxSHI0eDQ3d2ppaEVDSGt3MGlyN3ZSOU10UUpqUQ?oc=5",
      "summary": "European Luxury Stocks Slump on Trump’s Tariff Threat&nbsp;&nbsp;WSJ",
      "published": "2026-01-19T08:00:00+00:00",
      "source": "WSJ (via GNews)",
      "groups": [
        "Geopolitics",
        "Global Finance"
      ],
      "matched": [
        "Trump",
        "tariff"
      ],
      "big": false,
      "id": "42699f30f7b7f0e6"
    },
    {
      "title": "Indonesia and EU to sign agreement on 80% tariff-free exports - IDNFinancials.com",
      "link": "https://news.google.com/rss/articles/CBMiowFBVV95cUxOSlZJRm5MUlRSMFd1ZFpwVkZIUlhuVjk1TGpKdk54cExjNlRwb0x0QldUN3ZpTFJyYWFYd0ZaSDRZQzJWVWN5QzFrSWpiaElubjE2cldmcmZsY1U2LXd0QmxuOUt5S0pRRTEzeW5LMWVVSkt2cmJTcDNsX0sxWGVONmdvc09KUW4xaldxNG1kSm55bm4xS2RGeXpJRnZ0QzlMbUpB?oc=5",
      "summary": "Indonesia and EU to sign agreement on 80% tariff-free exports&nbsp;&nbsp;IDNFinancials.com",
      "published": "2025-09-17T07:00:00+00:00",
      "source": "Financial Times (via GNews)",
      "groups": [
        "Global Finance"
      ],
      "matched": [
        "tariff"
      ],
      "big": true,
      "id": "c7657ca7600604c0"
    },
    {
      "title": "Oxford Industries Profit Beats Expectations Amid Tariff Mitigation Efforts - WSJ",
      "link": "https://news.google.com/rss/articles/CBMivgFBVV95cUxNUkZENkFKcnZkNXl1RG5sWVZtNWFQb2dvZ2dsVTUwemJ3MDBZbk5mdExZQ25yWnMzZTdNSDZ2OEFHUTN6UFpLT2ZfcGgtSXo3ZDBCUndYZnZSUDVrMnNjMFlPSjcxdzB0MDd5VDd6c05OSXVQTUdiUkJwejBqdGRvV1NzN25DdVROcVNaMTR0N3MzQVVXV1lZd1dtSlZia0lhOVhzcVJURlZwWGt1cDF0UFBBRUNWMElQRmlkM0NR?oc=5",
      "summary": "Oxford Industries Profit Beats Expectations Amid Tariff Mitigation Efforts&nbsp;&nbsp;WSJ",
      "published": "2025-09-10T07:00:00+00:00",
      "source": "WSJ (via GNews)",
      "groups": [
        "Global Finance"
      ],
      "matched": [
        "tariff"
      ],
      "big": false,
      "id": "037e084b56ba9310"
    },
    {
      "title": "Indonesia intervenes to stem rupiah's slide after currency hits 4-year low - Reuters",
      "link": "https://news.google.com/rss/articles/CBMiwwFBVV95cUxNTldDa3Ryb1Q3dDE2Q0pNY0dPY2lNMHBEWE45T0RIWHdMUm1tMFEtVk1wdDc4X3V6R0VXLXYxdThVcGZ3Q192LURJb1FJLURwcjIwZloxcHhCcnFTN1BXRmdUVFl3RUJacm8tQ2g0TnlSUmsxdEZlV2tycnNHR3dqSVJabDk4U2plWVI2bHNVMjc5SC1GRGdrMjItak12eDFpYjBrUU42bXNkSVF4NnRkMElBT2s1ZjRGdmhEcjlmZUY1V1k?oc=5",
      "summary": "Indonesia intervenes to stem rupiah's slide after currency hits 4-year low&nbsp;&nbsp;Reuters",
      "published": "2024-04-16T07:00:00+00:00",
      "source": "Reuters – Indonesia",
      "groups": [
        "Macro / Economy"
      ],
      "matched": [
        "rupiah"
      ],
      "big": true,
      "id": "8669162f5e9c7e17"
    }
  ]
}